Classfile /Users/aclement/forks/spring-init-experiment/modules/library/target/classes/boot/autoconfigure/gson/GsonAutoConfigurationModule.class
  Last modified Oct 12, 2018; size 1763 bytes
  MD5 checksum 0994fae6448bd08e69eb8dfadb084f73
  Compiled from "GsonAutoConfigurationModule.java"
public class boot.autoconfigure.gson.GsonAutoConfigurationModule implements slim.Module
  minor version: 0
  major version: 52
  flags: ACC_PUBLIC, ACC_SUPER
Constant pool:
   #1 = Class              #2             // boot/autoconfigure/gson/GsonAutoConfigurationModule
   #2 = Utf8               boot/autoconfigure/gson/GsonAutoConfigurationModule
   #3 = Class              #4             // java/lang/Object
   #4 = Utf8               java/lang/Object
   #5 = Class              #6             // slim/Module
   #6 = Utf8               slim/Module
   #7 = Utf8               <init>
   #8 = Utf8               ()V
   #9 = Utf8               Code
  #10 = Methodref          #3.#11         // java/lang/Object."<init>":()V
  #11 = NameAndType        #7:#8          // "<init>":()V
  #12 = Utf8               LineNumberTable
  #13 = Utf8               LocalVariableTable
  #14 = Utf8               this
  #15 = Utf8               Lboot/autoconfigure/gson/GsonAutoConfigurationModule;
  #16 = Utf8               initializers
  #17 = Utf8               ()Ljava/util/List;
  #18 = Utf8               Signature
  #19 = Utf8               ()Ljava/util/List<Lorg/springframework/context/ApplicationContextInitializer<Lorg/springframework/context/support/GenericApplicationContext;>;>;
  #20 = Fieldref           #21.#23        // java/lang/System.out:Ljava/io/PrintStream;
  #21 = Class              #22            // java/lang/System
  #22 = Utf8               java/lang/System
  #23 = NameAndType        #24:#25        // out:Ljava/io/PrintStream;
  #24 = Utf8               out
  #25 = Utf8               Ljava/io/PrintStream;
  #26 = String             #27            // Wibble!
  #27 = Utf8               Wibble!
  #28 = Methodref          #29.#31        // java/io/PrintStream.println:(Ljava/lang/String;)V
  #29 = Class              #30            // java/io/PrintStream
  #30 = Utf8               java/io/PrintStream
  #31 = NameAndType        #32:#33        // println:(Ljava/lang/String;)V
  #32 = Utf8               println
  #33 = Utf8               (Ljava/lang/String;)V
  #34 = Class              #35            // org/springframework/context/ApplicationContextInitializer
  #35 = Utf8               org/springframework/context/ApplicationContextInitializer
  #36 = Methodref          #1.#37         // boot/autoconfigure/gson/GsonAutoConfigurationModule.initializer:()Lorg/springframework/context/ApplicationContextInitializer;
  #37 = NameAndType        #38:#39        // initializer:()Lorg/springframework/context/ApplicationContextInitializer;
  #38 = Utf8               initializer
  #39 = Utf8               ()Lorg/springframework/context/ApplicationContextInitializer;
  #40 = Methodref          #41.#43        // java/util/Arrays.asList:([Ljava/lang/Object;)Ljava/util/List;
  #41 = Class              #42            // java/util/Arrays
  #42 = Utf8               java/util/Arrays
  #43 = NameAndType        #44:#45        // asList:([Ljava/lang/Object;)Ljava/util/List;
  #44 = Utf8               asList
  #45 = Utf8               ([Ljava/lang/Object;)Ljava/util/List;
  #46 = Utf8               ()Lorg/springframework/context/ApplicationContextInitializer<Lorg/springframework/context/support/GenericApplicationContext;>;
  #47 = Class              #48            // boot/autoconfigure/gson/GsonAutoConfigurationModule$Initializer
  #48 = Utf8               boot/autoconfigure/gson/GsonAutoConfigurationModule$Initializer
  #49 = Methodref          #47.#50        // boot/autoconfigure/gson/GsonAutoConfigurationModule$Initializer."<init>":(Lboot/autoconfigure/gson/GsonAutoConfigurationModule$Initializer;)V
  #50 = NameAndType        #7:#51         // "<init>":(Lboot/autoconfigure/gson/GsonAutoConfigurationModule$Initializer;)V
  #51 = Utf8               (Lboot/autoconfigure/gson/GsonAutoConfigurationModule$Initializer;)V
  #52 = Utf8               SourceFile
  #53 = Utf8               GsonAutoConfigurationModule.java
  #54 = Utf8               RuntimeVisibleAnnotations
  #55 = Utf8               Lorg/springframework/context/annotation/Configuration;
  #56 = Utf8               Lorg/springframework/context/annotation/Import;
  #57 = Utf8               value
  #58 = Utf8               Lorg/springframework/boot/autoconfigure/gson/GsonAutoConfiguration;
  #59 = Utf8               Lslim/ImportModule;
  #60 = Utf8               module
  #61 = Utf8               Lboot/autoconfigure/context/ContextAutoConfigurationModule;
  #62 = Utf8               InnerClasses
  #63 = Utf8               Initializer
{
  public boot.autoconfigure.gson.GsonAutoConfigurationModule();
    descriptor: ()V
    flags: ACC_PUBLIC
    Code:
      stack=1, locals=1, args_size=1
         0: aload_0
         1: invokespecial #10                 // Method java/lang/Object."<init>":()V
         4: return
      LineNumberTable:
        line 47: 0
      LocalVariableTable:
        Start  Length  Slot  Name   Signature
            0       5     0  this   Lboot/autoconfigure/gson/GsonAutoConfigurationModule;

  public java.util.List<org.springframework.context.ApplicationContextInitializer<org.springframework.context.support.GenericApplicationContext>> initializers();
    descriptor: ()Ljava/util/List;
    flags: ACC_PUBLIC
    Signature: #19                          // ()Ljava/util/List<Lorg/springframework/context/ApplicationContextInitializer<Lorg/springframework/context/support/GenericApplicationContext;>;>;
    Code:
      stack=4, locals=1, args_size=1
         0: getstatic     #20                 // Field java/lang/System.out:Ljava/io/PrintStream;
         3: ldc           #26                 // String Wibble!
         5: invokevirtual #28                 // Method java/io/PrintStream.println:(Ljava/lang/String;)V
         8: iconst_1
         9: anewarray     #34                 // class org/springframework/context/ApplicationContextInitializer
        12: dup
        13: iconst_0
        14: invokestatic  #36                 // Method initializer:()Lorg/springframework/context/ApplicationContextInitializer;
        17: aastore
        18: invokestatic  #40                 // Method java/util/Arrays.asList:([Ljava/lang/Object;)Ljava/util/List;
        21: areturn
      LineNumberTable:
        line 51: 0
        line 52: 8
      LocalVariableTable:
        Start  Length  Slot  Name   Signature
            0      22     0  this   Lboot/autoconfigure/gson/GsonAutoConfigurationModule;

  public static org.springframework.context.ApplicationContextInitializer<org.springframework.context.support.GenericApplicationContext> initializer();
    descriptor: ()Lorg/springframework/context/ApplicationContextInitializer;
    flags: ACC_PUBLIC, ACC_STATIC
    Signature: #46                          // ()Lorg/springframework/context/ApplicationContextInitializer<Lorg/springframework/context/support/GenericApplicationContext;>;
    Code:
      stack=3, locals=0, args_size=0
         0: new           #47                 // class boot/autoconfigure/gson/GsonAutoConfigurationModule$Initializer
         3: dup
         4: aconst_null
         5: invokespecial #49                 // Method boot/autoconfigure/gson/GsonAutoConfigurationModule$Initializer."<init>":(Lboot/autoconfigure/gson/GsonAutoConfigurationModule$Initializer;)V
         8: areturn
      LineNumberTable:
        line 56: 0
      LocalVariableTable:
        Start  Length  Slot  Name   Signature
}
SourceFile: "GsonAutoConfigurationModule.java"
RuntimeVisibleAnnotations:
  0: #55()
  1: #56(#57=[c#58])
  2: #59(#60=[c#61])
InnerClasses:
     private static #63= #47 of #1; //Initializer=class boot/autoconfigure/gson/GsonAutoConfigurationModule$Initializer of class boot/autoconfigure/gson/GsonAutoConfigurationModule
