Classfile /Users/aclement/forks/spring-init-experiment/application/target/classes/org/springframework/boot/autoconfigure/gson/GsonAutoConfigurationModule$Initializer.class
  Last modified 19-Oct-2018; size 5516 bytes
  MD5 checksum 5800861d26a9d41704dc736e524354cd
class org.springframework.boot.autoconfigure.gson.GsonAutoConfigurationModule$Initializer extends java.lang.Object implements org.springframework.context.ApplicationContextInitializer<org.springframework.context.support.GenericApplicationContext>
  minor version: 0
  major version: 52
  flags: ACC_SUPER
Constant pool:
    #1 = Utf8               org/springframework/boot/autoconfigure/gson/GsonAutoConfigurationModule$Initializer
    #2 = Class              #1            // org/springframework/boot/autoconfigure/gson/GsonAutoConfigurationModule$Initializer
    #3 = Utf8               Ljava/lang/Object;Lorg/springframework/context/ApplicationContextInitializer<Lorg/springframework/context/support/GenericApplicationContext;>;
    #4 = Utf8               java/lang/Object
    #5 = Class              #4            // java/lang/Object
    #6 = Utf8               org/springframework/context/ApplicationContextInitializer
    #7 = Class              #6            // org/springframework/context/ApplicationContextInitializer
    #8 = Utf8               Lslim/InitializerMapping;
    #9 = Utf8               value
   #10 = Utf8               Lorg/springframework/boot/autoconfigure/gson/GsonAutoConfiguration;
   #11 = Utf8               initialize
   #12 = Utf8               (Lorg/springframework/context/support/GenericApplicationContext;)V
   #13 = Utf8               java/lang/System
   #14 = Class              #13           // java/lang/System
   #15 = Utf8               out
   #16 = Utf8               Ljava/io/PrintStream;
   #17 = NameAndType        #15:#16       // out:Ljava/io/PrintStream;
   #18 = Fieldref           #14.#17       // java/lang/System.out:Ljava/io/PrintStream;
   #19 = Utf8               :debug: Processing type level conditions on org.springframework.boot.autoconfigure.gson.GsonAutoConfiguration
   #20 = String             #19           // :debug: Processing type level conditions on org.springframework.boot.autoconfigure.gson.GsonAutoConfiguration
   #21 = Utf8               java/io/PrintStream
   #22 = Class              #21           // java/io/PrintStream
   #23 = Utf8               println
   #24 = Utf8               (Ljava/lang/String;)V
   #25 = NameAndType        #23:#24       // println:(Ljava/lang/String;)V
   #26 = Methodref          #22.#25       // java/io/PrintStream.println:(Ljava/lang/String;)V
   #27 = Utf8               com.google.gson.Gson
   #28 = String             #27           // com.google.gson.Gson
   #29 = Utf8               org/springframework/util/ClassUtils
   #30 = Class              #29           // org/springframework/util/ClassUtils
   #31 = Utf8               isPresent
   #32 = Utf8               (Ljava/lang/String;Ljava/lang/ClassLoader;)Z
   #33 = NameAndType        #31:#32       // isPresent:(Ljava/lang/String;Ljava/lang/ClassLoader;)Z
   #34 = Methodref          #30.#33       // org/springframework/util/ClassUtils.isPresent:(Ljava/lang/String;Ljava/lang/ClassLoader;)Z
   #35 = Utf8               :debug: Passed condition checks on org.springframework.boot.autoconfigure.gson.GsonAutoConfiguration
   #36 = String             #35           // :debug: Passed condition checks on org.springframework.boot.autoconfigure.gson.GsonAutoConfiguration
   #37 = Utf8               org/springframework/beans/factory/config/BeanDefinitionCustomizer
   #38 = Class              #37           // org/springframework/beans/factory/config/BeanDefinitionCustomizer
   #39 = Utf8               org/springframework/boot/autoconfigure/gson/GsonProperties
   #40 = Class              #39           // org/springframework/boot/autoconfigure/gson/GsonProperties
   #41 = Utf8               ()Ljava/lang/Object;
   #42 = MethodType         #41           //  ()Ljava/lang/Object;
   #43 = Utf8               init_GsonProperties
   #44 = Utf8               (Lorg/springframework/beans/factory/BeanFactory;)Lorg/springframework/boot/autoconfigure/gson/GsonProperties;
   #45 = NameAndType        #43:#44       // init_GsonProperties:(Lorg/springframework/beans/factory/BeanFactory;)Lorg/springframework/boot/autoconfigure/gson/GsonProperties;
   #46 = Methodref          #2.#45        // org/springframework/boot/autoconfigure/gson/GsonAutoConfigurationModule$Initializer.init_GsonProperties:(Lorg/springframework/beans/factory/BeanFactory;)Lorg/springframework/boot/autoconfigure/gson/GsonProperties;
   #47 = MethodHandle       #6:#46        // invokestatic org/springframework/boot/autoconfigure/gson/GsonAutoConfigurationModule$Initializer.init_GsonProperties:(Lorg/springframework/beans/factory/BeanFactory;)Lorg/springframework/boot/autoconfigure/gson/GsonProperties;
   #48 = Utf8               ()Lorg/springframework/boot/autoconfigure/gson/GsonProperties;
   #49 = MethodType         #48           //  ()Lorg/springframework/boot/autoconfigure/gson/GsonProperties;
   #50 = Utf8               java/lang/invoke/LambdaMetafactory
   #51 = Class              #50           // java/lang/invoke/LambdaMetafactory
   #52 = Utf8               metafactory
   #53 = Utf8               (Ljava/lang/invoke/MethodHandles$Lookup;Ljava/lang/String;Ljava/lang/invoke/MethodType;Ljava/lang/invoke/MethodType;Ljava/lang/invoke/MethodHandle;Ljava/lang/invoke/MethodType;)Ljava/lang/invoke/CallSite;
   #54 = NameAndType        #52:#53       // metafactory:(Ljava/lang/invoke/MethodHandles$Lookup;Ljava/lang/String;Ljava/lang/invoke/MethodType;Ljava/lang/invoke/MethodType;Ljava/lang/invoke/MethodHandle;Ljava/lang/invoke/MethodType;)Ljava/lang/invoke/CallSite;
   #55 = Methodref          #51.#54       // java/lang/invoke/LambdaMetafactory.metafactory:(Ljava/lang/invoke/MethodHandles$Lookup;Ljava/lang/String;Ljava/lang/invoke/MethodType;Ljava/lang/invoke/MethodType;Ljava/lang/invoke/MethodHandle;Ljava/lang/invoke/MethodType;)Ljava/lang/invoke/CallSite;
   #56 = MethodHandle       #6:#55        // invokestatic java/lang/invoke/LambdaMetafactory.metafactory:(Ljava/lang/invoke/MethodHandles$Lookup;Ljava/lang/String;Ljava/lang/invoke/MethodType;Ljava/lang/invoke/MethodType;Ljava/lang/invoke/MethodHandle;Ljava/lang/invoke/MethodType;)Ljava/lang/invoke/CallSite;
   #57 = Utf8               get
   #58 = Utf8               (Lorg/springframework/beans/factory/BeanFactory;)Ljava/util/function/Supplier;
   #59 = NameAndType        #57:#58       // get:(Lorg/springframework/beans/factory/BeanFactory;)Ljava/util/function/Supplier;
   #60 = InvokeDynamic      #0:#59        // #0:get:(Lorg/springframework/beans/factory/BeanFactory;)Ljava/util/function/Supplier;
   #61 = Utf8               org/springframework/context/support/GenericApplicationContext
   #62 = Class              #61           // org/springframework/context/support/GenericApplicationContext
   #63 = Utf8               registerBean
   #64 = Utf8               (Ljava/lang/Class;Ljava/util/function/Supplier;[Lorg/springframework/beans/factory/config/BeanDefinitionCustomizer;)V
   #65 = NameAndType        #63:#64       // registerBean:(Ljava/lang/Class;Ljava/util/function/Supplier;[Lorg/springframework/beans/factory/config/BeanDefinitionCustomizer;)V
   #66 = Methodref          #62.#65       // org/springframework/context/support/GenericApplicationContext.registerBean:(Ljava/lang/Class;Ljava/util/function/Supplier;[Lorg/springframework/beans/factory/config/BeanDefinitionCustomizer;)V
   #67 = Utf8               org/springframework/boot/autoconfigure/gson/GsonAutoConfiguration
   #68 = Class              #67           // org/springframework/boot/autoconfigure/gson/GsonAutoConfiguration
   #69 = Utf8               (Ljava/lang/Class;[Lorg/springframework/beans/factory/config/BeanDefinitionCustomizer;)V
   #70 = NameAndType        #63:#69       // registerBean:(Ljava/lang/Class;[Lorg/springframework/beans/factory/config/BeanDefinitionCustomizer;)V
   #71 = Methodref          #62.#70       // org/springframework/context/support/GenericApplicationContext.registerBean:(Ljava/lang/Class;[Lorg/springframework/beans/factory/config/BeanDefinitionCustomizer;)V
   #72 = Utf8               :debug: Checking conditions before calling registerBean for bean factory method gsonBuilder
   #73 = String             #72           // :debug: Checking conditions before calling registerBean for bean factory method gsonBuilder
   #74 = Utf8               com/google/gson/GsonBuilder
   #75 = Class              #74           // com/google/gson/GsonBuilder
   #76 = Utf8               org/springframework/beans/factory/ListableBeanFactory
   #77 = Class              #76           // org/springframework/beans/factory/ListableBeanFactory
   #78 = Utf8               getBeanNamesForType
   #79 = Utf8               (Ljava/lang/Class;)[Ljava/lang/String;
   #80 = NameAndType        #78:#79       // getBeanNamesForType:(Ljava/lang/Class;)[Ljava/lang/String;
   #81 = InterfaceMethodref #77.#80       // org/springframework/beans/factory/ListableBeanFactory.getBeanNamesForType:(Ljava/lang/Class;)[Ljava/lang/String;
   #82 = Utf8               :debug: Calling registerBean for bean factory method gsonBuilder
   #83 = String             #82           // :debug: Calling registerBean for bean factory method gsonBuilder
   #84 = Utf8               init_gsonBuilder
   #85 = Utf8               (Lorg/springframework/beans/factory/BeanFactory;)Lcom/google/gson/GsonBuilder;
   #86 = NameAndType        #84:#85       // init_gsonBuilder:(Lorg/springframework/beans/factory/BeanFactory;)Lcom/google/gson/GsonBuilder;
   #87 = Methodref          #2.#86        // org/springframework/boot/autoconfigure/gson/GsonAutoConfigurationModule$Initializer.init_gsonBuilder:(Lorg/springframework/beans/factory/BeanFactory;)Lcom/google/gson/GsonBuilder;
   #88 = MethodHandle       #6:#87        // invokestatic org/springframework/boot/autoconfigure/gson/GsonAutoConfigurationModule$Initializer.init_gsonBuilder:(Lorg/springframework/beans/factory/BeanFactory;)Lcom/google/gson/GsonBuilder;
   #89 = Utf8               ()Lcom/google/gson/GsonBuilder;
   #90 = MethodType         #89           //  ()Lcom/google/gson/GsonBuilder;
   #91 = InvokeDynamic      #1:#59        // #1:get:(Lorg/springframework/beans/factory/BeanFactory;)Ljava/util/function/Supplier;
   #92 = Utf8               :debug: Checking conditions before calling registerBean for bean factory method gson
   #93 = String             #92           // :debug: Checking conditions before calling registerBean for bean factory method gson
   #94 = Utf8               com/google/gson/Gson
   #95 = Class              #94           // com/google/gson/Gson
   #96 = Utf8               :debug: Calling registerBean for bean factory method gson
   #97 = String             #96           // :debug: Calling registerBean for bean factory method gson
   #98 = Utf8               init_gson
   #99 = Utf8               (Lorg/springframework/beans/factory/BeanFactory;)Lcom/google/gson/Gson;
  #100 = NameAndType        #98:#99       // init_gson:(Lorg/springframework/beans/factory/BeanFactory;)Lcom/google/gson/Gson;
  #101 = Methodref          #2.#100       // org/springframework/boot/autoconfigure/gson/GsonAutoConfigurationModule$Initializer.init_gson:(Lorg/springframework/beans/factory/BeanFactory;)Lcom/google/gson/Gson;
  #102 = MethodHandle       #6:#101       // invokestatic org/springframework/boot/autoconfigure/gson/GsonAutoConfigurationModule$Initializer.init_gson:(Lorg/springframework/beans/factory/BeanFactory;)Lcom/google/gson/Gson;
  #103 = Utf8               ()Lcom/google/gson/Gson;
  #104 = MethodType         #103          //  ()Lcom/google/gson/Gson;
  #105 = InvokeDynamic      #2:#59        // #2:get:(Lorg/springframework/beans/factory/BeanFactory;)Ljava/util/function/Supplier;
  #106 = Utf8               :debug: Checking conditions before calling registerBean for bean factory method standardGsonBuilderCustomizer
  #107 = String             #106          // :debug: Checking conditions before calling registerBean for bean factory method standardGsonBuilderCustomizer
  #108 = Utf8               :debug: Calling registerBean for bean factory method standardGsonBuilderCustomizer
  #109 = String             #108          // :debug: Calling registerBean for bean factory method standardGsonBuilderCustomizer
  #110 = Utf8               org/springframework/boot/autoconfigure/gson/GsonAutoConfiguration$StandardGsonBuilderCustomizer
  #111 = Class              #110          // org/springframework/boot/autoconfigure/gson/GsonAutoConfiguration$StandardGsonBuilderCustomizer
  #112 = Utf8               init_standardGsonBuilderCustomizer
  #113 = Utf8               (Lorg/springframework/beans/factory/BeanFactory;)Lorg/springframework/boot/autoconfigure/gson/GsonAutoConfiguration$StandardGsonBuilderCustomizer;
  #114 = NameAndType        #112:#113     // init_standardGsonBuilderCustomizer:(Lorg/springframework/beans/factory/BeanFactory;)Lorg/springframework/boot/autoconfigure/gson/GsonAutoConfiguration$StandardGsonBuilderCustomizer;
  #115 = Methodref          #2.#114       // org/springframework/boot/autoconfigure/gson/GsonAutoConfigurationModule$Initializer.init_standardGsonBuilderCustomizer:(Lorg/springframework/beans/factory/BeanFactory;)Lorg/springframework/boot/autoconfigure/gson/GsonAutoConfiguration$StandardGsonBuilderCustomizer;
  #116 = MethodHandle       #6:#115       // invokestatic org/springframework/boot/autoconfigure/gson/GsonAutoConfigurationModule$Initializer.init_standardGsonBuilderCustomizer:(Lorg/springframework/beans/factory/BeanFactory;)Lorg/springframework/boot/autoconfigure/gson/GsonAutoConfiguration$StandardGsonBuilderCustomizer;
  #117 = Utf8               ()Lorg/springframework/boot/autoconfigure/gson/GsonAutoConfiguration$StandardGsonBuilderCustomizer;
  #118 = MethodType         #117          //  ()Lorg/springframework/boot/autoconfigure/gson/GsonAutoConfiguration$StandardGsonBuilderCustomizer;
  #119 = InvokeDynamic      #3:#59        // #3:get:(Lorg/springframework/beans/factory/BeanFactory;)Ljava/util/function/Supplier;
  #120 = Utf8               [Lorg/springframework/beans/factory/config/BeanDefinitionCustomizer;
  #121 = Class              #120          // "[Lorg/springframework/beans/factory/config/BeanDefinitionCustomizer;"
  #122 = Utf8               (Lorg/springframework/context/ConfigurableApplicationContext;)V
  #123 = NameAndType        #11:#12       // initialize:(Lorg/springframework/context/support/GenericApplicationContext;)V
  #124 = Methodref          #2.#123       // org/springframework/boot/autoconfigure/gson/GsonAutoConfigurationModule$Initializer.initialize:(Lorg/springframework/context/support/GenericApplicationContext;)V
  #125 = Utf8               <init>
  #126 = Utf8               (Lorg/springframework/boot/autoconfigure/gson/GsonAutoConfigurationModule$Initializer;)V
  #127 = Utf8               ()V
  #128 = NameAndType        #125:#127     // "<init>":()V
  #129 = Methodref          #5.#128       // java/lang/Object."<init>":()V
  #130 = Methodref          #40.#128      // org/springframework/boot/autoconfigure/gson/GsonProperties."<init>":()V
  #131 = Utf8               :debug: execution of lambda for gsonBuilder
  #132 = String             #131          // :debug: execution of lambda for gsonBuilder
  #133 = Utf8               org/springframework/beans/factory/BeanFactory
  #134 = Class              #133          // org/springframework/beans/factory/BeanFactory
  #135 = Utf8               getBean
  #136 = Utf8               (Ljava/lang/Class;)Ljava/lang/Object;
  #137 = NameAndType        #135:#136     // getBean:(Ljava/lang/Class;)Ljava/lang/Object;
  #138 = InterfaceMethodref #134.#137     // org/springframework/beans/factory/BeanFactory.getBean:(Ljava/lang/Class;)Ljava/lang/Object;
  #139 = Utf8               java/util/ArrayList
  #140 = Class              #139          // java/util/ArrayList
  #141 = Utf8               org/springframework/boot/autoconfigure/gson/GsonBuilderCustomizer
  #142 = Class              #141          // org/springframework/boot/autoconfigure/gson/GsonBuilderCustomizer
  #143 = Utf8               org/springframework/context/support/AbstractApplicationContext
  #144 = Class              #143          // org/springframework/context/support/AbstractApplicationContext
  #145 = Utf8               getBeansOfType
  #146 = Utf8               (Ljava/lang/Class;)Ljava/util/Map;
  #147 = NameAndType        #145:#146     // getBeansOfType:(Ljava/lang/Class;)Ljava/util/Map;
  #148 = Methodref          #144.#147     // org/springframework/context/support/AbstractApplicationContext.getBeansOfType:(Ljava/lang/Class;)Ljava/util/Map;
  #149 = Utf8               java/util/Map
  #150 = Class              #149          // java/util/Map
  #151 = Utf8               values
  #152 = Utf8               ()Ljava/util/Collection;
  #153 = NameAndType        #151:#152     // values:()Ljava/util/Collection;
  #154 = InterfaceMethodref #150.#153     // java/util/Map.values:()Ljava/util/Collection;
  #155 = Utf8               (Ljava/util/Collection;)V
  #156 = NameAndType        #125:#155     // "<init>":(Ljava/util/Collection;)V
  #157 = Methodref          #140.#156     // java/util/ArrayList."<init>":(Ljava/util/Collection;)V
  #158 = Utf8               java/util/List
  #159 = Class              #158          // java/util/List
  #160 = Utf8               gsonBuilder
  #161 = Utf8               (Ljava/util/List;)Lcom/google/gson/GsonBuilder;
  #162 = NameAndType        #160:#161     // gsonBuilder:(Ljava/util/List;)Lcom/google/gson/GsonBuilder;
  #163 = Methodref          #68.#162      // org/springframework/boot/autoconfigure/gson/GsonAutoConfiguration.gsonBuilder:(Ljava/util/List;)Lcom/google/gson/GsonBuilder;
  #164 = Utf8               :debug: execution of lambda for gson
  #165 = String             #164          // :debug: execution of lambda for gson
  #166 = Utf8               gson
  #167 = Utf8               (Lcom/google/gson/GsonBuilder;)Lcom/google/gson/Gson;
  #168 = NameAndType        #166:#167     // gson:(Lcom/google/gson/GsonBuilder;)Lcom/google/gson/Gson;
  #169 = Methodref          #68.#168      // org/springframework/boot/autoconfigure/gson/GsonAutoConfiguration.gson:(Lcom/google/gson/GsonBuilder;)Lcom/google/gson/Gson;
  #170 = Utf8               :debug: execution of lambda for standardGsonBuilderCustomizer
  #171 = String             #170          // :debug: execution of lambda for standardGsonBuilderCustomizer
  #172 = Utf8               standardGsonBuilderCustomizer
  #173 = Utf8               (Lorg/springframework/boot/autoconfigure/gson/GsonProperties;)Lorg/springframework/boot/autoconfigure/gson/GsonAutoConfiguration$StandardGsonBuilderCustomizer;
  #174 = NameAndType        #172:#173     // standardGsonBuilderCustomizer:(Lorg/springframework/boot/autoconfigure/gson/GsonProperties;)Lorg/springframework/boot/autoconfigure/gson/GsonAutoConfiguration$StandardGsonBuilderCustomizer;
  #175 = Methodref          #68.#174      // org/springframework/boot/autoconfigure/gson/GsonAutoConfiguration.standardGsonBuilderCustomizer:(Lorg/springframework/boot/autoconfigure/gson/GsonProperties;)Lorg/springframework/boot/autoconfigure/gson/GsonAutoConfiguration$StandardGsonBuilderCustomizer;
  #176 = Utf8               Code
  #177 = Utf8               StackMapTable
  #178 = Utf8               Signature
  #179 = Utf8               RuntimeVisibleAnnotations
  #180 = Utf8               BootstrapMethods
{
  public void initialize(org.springframework.context.support.GenericApplicationContext);
    descriptor: (Lorg/springframework/context/support/GenericApplicationContext;)V
    flags: ACC_PUBLIC
    Code:
      stack=4, locals=3, args_size=2
         0: getstatic     #18                 // Field java/lang/System.out:Ljava/io/PrintStream;
         3: ldc           #20                 // String :debug: Processing type level conditions on org.springframework.boot.autoconfigure.gson.GsonAutoConfiguration
         5: invokevirtual #26                 // Method java/io/PrintStream.println:(Ljava/lang/String;)V
         8: ldc           #28                 // String com.google.gson.Gson
        10: aconst_null
        11: invokestatic  #34                 // Method org/springframework/util/ClassUtils.isPresent:(Ljava/lang/String;Ljava/lang/ClassLoader;)Z
        14: ifeq          173
        17: getstatic     #18                 // Field java/lang/System.out:Ljava/io/PrintStream;
        20: ldc           #36                 // String :debug: Passed condition checks on org.springframework.boot.autoconfigure.gson.GsonAutoConfiguration
        22: invokevirtual #26                 // Method java/io/PrintStream.println:(Ljava/lang/String;)V
        25: iconst_0
        26: anewarray     #38                 // class org/springframework/beans/factory/config/BeanDefinitionCustomizer
        29: astore_2
        30: aload_1
        31: ldc           #40                 // class org/springframework/boot/autoconfigure/gson/GsonProperties
        33: aload_1
        34: invokedynamic #60,  0             // InvokeDynamic #0:get:(Lorg/springframework/beans/factory/BeanFactory;)Ljava/util/function/Supplier;
        39: iconst_0
        40: anewarray     #38                 // class org/springframework/beans/factory/config/BeanDefinitionCustomizer
        43: invokevirtual #66                 // Method org/springframework/context/support/GenericApplicationContext.registerBean:(Ljava/lang/Class;Ljava/util/function/Supplier;[Lorg/springframework/beans/factory/config/BeanDefinitionCustomizer;)V
        46: aload_1
        47: ldc           #68                 // class org/springframework/boot/autoconfigure/gson/GsonAutoConfiguration
        49: aload_2
        50: invokevirtual #71                 // Method org/springframework/context/support/GenericApplicationContext.registerBean:(Ljava/lang/Class;[Lorg/springframework/beans/factory/config/BeanDefinitionCustomizer;)V
        53: getstatic     #18                 // Field java/lang/System.out:Ljava/io/PrintStream;
        56: ldc           #73                 // String :debug: Checking conditions before calling registerBean for bean factory method gsonBuilder
        58: invokevirtual #26                 // Method java/io/PrintStream.println:(Ljava/lang/String;)V
        61: aload_1
        62: ldc           #75                 // class com/google/gson/GsonBuilder
        64: invokeinterface #81,  2           // InterfaceMethod org/springframework/beans/factory/ListableBeanFactory.getBeanNamesForType:(Ljava/lang/Class;)[Ljava/lang/String;
        69: arraylength
        70: ifne          97
        73: getstatic     #18                 // Field java/lang/System.out:Ljava/io/PrintStream;
        76: ldc           #83                 // String :debug: Calling registerBean for bean factory method gsonBuilder
        78: invokevirtual #26                 // Method java/io/PrintStream.println:(Ljava/lang/String;)V
        81: aload_1
        82: ldc           #75                 // class com/google/gson/GsonBuilder
        84: aload_1
        85: invokedynamic #91,  0             // InvokeDynamic #1:get:(Lorg/springframework/beans/factory/BeanFactory;)Ljava/util/function/Supplier;
        90: iconst_0
        91: anewarray     #38                 // class org/springframework/beans/factory/config/BeanDefinitionCustomizer
        94: invokevirtual #66                 // Method org/springframework/context/support/GenericApplicationContext.registerBean:(Ljava/lang/Class;Ljava/util/function/Supplier;[Lorg/springframework/beans/factory/config/BeanDefinitionCustomizer;)V
        97: getstatic     #18                 // Field java/lang/System.out:Ljava/io/PrintStream;
       100: ldc           #93                 // String :debug: Checking conditions before calling registerBean for bean factory method gson
       102: invokevirtual #26                 // Method java/io/PrintStream.println:(Ljava/lang/String;)V
       105: aload_1
       106: ldc           #95                 // class com/google/gson/Gson
       108: invokeinterface #81,  2           // InterfaceMethod org/springframework/beans/factory/ListableBeanFactory.getBeanNamesForType:(Ljava/lang/Class;)[Ljava/lang/String;
       113: arraylength
       114: ifne          141
       117: getstatic     #18                 // Field java/lang/System.out:Ljava/io/PrintStream;
       120: ldc           #97                 // String :debug: Calling registerBean for bean factory method gson
       122: invokevirtual #26                 // Method java/io/PrintStream.println:(Ljava/lang/String;)V
       125: aload_1
       126: ldc           #95                 // class com/google/gson/Gson
       128: aload_1
       129: invokedynamic #105,  0            // InvokeDynamic #2:get:(Lorg/springframework/beans/factory/BeanFactory;)Ljava/util/function/Supplier;
       134: iconst_0
       135: anewarray     #38                 // class org/springframework/beans/factory/config/BeanDefinitionCustomizer
       138: invokevirtual #66                 // Method org/springframework/context/support/GenericApplicationContext.registerBean:(Ljava/lang/Class;Ljava/util/function/Supplier;[Lorg/springframework/beans/factory/config/BeanDefinitionCustomizer;)V
       141: getstatic     #18                 // Field java/lang/System.out:Ljava/io/PrintStream;
       144: ldc           #107                // String :debug: Checking conditions before calling registerBean for bean factory method standardGsonBuilderCustomizer
       146: invokevirtual #26                 // Method java/io/PrintStream.println:(Ljava/lang/String;)V
       149: getstatic     #18                 // Field java/lang/System.out:Ljava/io/PrintStream;
       152: ldc           #109                // String :debug: Calling registerBean for bean factory method standardGsonBuilderCustomizer
       154: invokevirtual #26                 // Method java/io/PrintStream.println:(Ljava/lang/String;)V
       157: aload_1
       158: ldc           #111                // class org/springframework/boot/autoconfigure/gson/GsonAutoConfiguration$StandardGsonBuilderCustomizer
       160: aload_1
       161: invokedynamic #119,  0            // InvokeDynamic #3:get:(Lorg/springframework/beans/factory/BeanFactory;)Ljava/util/function/Supplier;
       166: iconst_0
       167: anewarray     #38                 // class org/springframework/beans/factory/config/BeanDefinitionCustomizer
       170: invokevirtual #66                 // Method org/springframework/context/support/GenericApplicationContext.registerBean:(Ljava/lang/Class;Ljava/util/function/Supplier;[Lorg/springframework/beans/factory/config/BeanDefinitionCustomizer;)V
       173: return
      StackMapTable: number_of_entries = 3
        frame_type = 252 /* append */
          offset_delta = 97
          locals = [ class "[Lorg/springframework/beans/factory/config/BeanDefinitionCustomizer;" ]
        frame_type = 43 /* same */
        frame_type = 250 /* chop */
          offset_delta = 31

  public void initialize(org.springframework.context.ConfigurableApplicationContext);
    descriptor: (Lorg/springframework/context/ConfigurableApplicationContext;)V
    flags: ACC_PUBLIC, ACC_BRIDGE, ACC_SYNTHETIC
    Code:
      stack=2, locals=2, args_size=2
         0: aload_0
         1: aload_1
         2: checkcast     #62                 // class org/springframework/context/support/GenericApplicationContext
         5: invokevirtual #124                // Method initialize:(Lorg/springframework/context/support/GenericApplicationContext;)V
         8: return

  org.springframework.boot.autoconfigure.gson.GsonAutoConfigurationModule$Initializer(org.springframework.boot.autoconfigure.gson.GsonAutoConfigurationModule$Initializer);
    descriptor: (Lorg/springframework/boot/autoconfigure/gson/GsonAutoConfigurationModule$Initializer;)V
    flags:
    Code:
      stack=2, locals=2, args_size=2
         0: aload_0
         1: dup
         2: invokespecial #129                // Method java/lang/Object."<init>":()V
         5: pop
         6: return

  private org.springframework.boot.autoconfigure.gson.GsonAutoConfigurationModule$Initializer();
    descriptor: ()V
    flags: ACC_PRIVATE
    Code:
      stack=2, locals=1, args_size=1
         0: aload_0
         1: dup
         2: invokespecial #129                // Method java/lang/Object."<init>":()V
         5: pop
         6: return

  private static org.springframework.boot.autoconfigure.gson.GsonProperties init_GsonProperties(org.springframework.beans.factory.BeanFactory);
    descriptor: (Lorg/springframework/beans/factory/BeanFactory;)Lorg/springframework/boot/autoconfigure/gson/GsonProperties;
    flags: ACC_PRIVATE, ACC_STATIC
    Code:
      stack=2, locals=1, args_size=1
         0: new           #40                 // class org/springframework/boot/autoconfigure/gson/GsonProperties
         3: dup
         4: invokespecial #130                // Method org/springframework/boot/autoconfigure/gson/GsonProperties."<init>":()V
         7: areturn

  private static com.google.gson.GsonBuilder init_gsonBuilder(org.springframework.beans.factory.BeanFactory);
    descriptor: (Lorg/springframework/beans/factory/BeanFactory;)Lcom/google/gson/GsonBuilder;
    flags: ACC_PRIVATE, ACC_STATIC
    Code:
      stack=5, locals=1, args_size=1
         0: getstatic     #18                 // Field java/lang/System.out:Ljava/io/PrintStream;
         3: ldc           #132                // String :debug: execution of lambda for gsonBuilder
         5: invokevirtual #26                 // Method java/io/PrintStream.println:(Ljava/lang/String;)V
         8: aload_0
         9: ldc           #68                 // class org/springframework/boot/autoconfigure/gson/GsonAutoConfiguration
        11: invokeinterface #138,  2          // InterfaceMethod org/springframework/beans/factory/BeanFactory.getBean:(Ljava/lang/Class;)Ljava/lang/Object;
        16: checkcast     #68                 // class org/springframework/boot/autoconfigure/gson/GsonAutoConfiguration
        19: new           #140                // class java/util/ArrayList
        22: dup
        23: aload_0
        24: ldc           #142                // class org/springframework/boot/autoconfigure/gson/GsonBuilderCustomizer
        26: checkcast     #144                // class org/springframework/context/support/AbstractApplicationContext
        29: invokevirtual #148                // Method org/springframework/context/support/AbstractApplicationContext.getBeansOfType:(Ljava/lang/Class;)Ljava/util/Map;
        32: invokeinterface #154,  1          // InterfaceMethod java/util/Map.values:()Ljava/util/Collection;
        37: invokespecial #157                // Method java/util/ArrayList."<init>":(Ljava/util/Collection;)V
        40: checkcast     #159                // class java/util/List
        43: invokevirtual #163                // Method org/springframework/boot/autoconfigure/gson/GsonAutoConfiguration.gsonBuilder:(Ljava/util/List;)Lcom/google/gson/GsonBuilder;
        46: areturn

  private static com.google.gson.Gson init_gson(org.springframework.beans.factory.BeanFactory);
    descriptor: (Lorg/springframework/beans/factory/BeanFactory;)Lcom/google/gson/Gson;
    flags: ACC_PRIVATE, ACC_STATIC
    Code:
      stack=3, locals=1, args_size=1
         0: getstatic     #18                 // Field java/lang/System.out:Ljava/io/PrintStream;
         3: ldc           #165                // String :debug: execution of lambda for gson
         5: invokevirtual #26                 // Method java/io/PrintStream.println:(Ljava/lang/String;)V
         8: aload_0
         9: ldc           #68                 // class org/springframework/boot/autoconfigure/gson/GsonAutoConfiguration
        11: invokeinterface #138,  2          // InterfaceMethod org/springframework/beans/factory/BeanFactory.getBean:(Ljava/lang/Class;)Ljava/lang/Object;
        16: checkcast     #68                 // class org/springframework/boot/autoconfigure/gson/GsonAutoConfiguration
        19: aload_0
        20: ldc           #75                 // class com/google/gson/GsonBuilder
        22: invokeinterface #138,  2          // InterfaceMethod org/springframework/beans/factory/BeanFactory.getBean:(Ljava/lang/Class;)Ljava/lang/Object;
        27: checkcast     #75                 // class com/google/gson/GsonBuilder
        30: invokevirtual #169                // Method org/springframework/boot/autoconfigure/gson/GsonAutoConfiguration.gson:(Lcom/google/gson/GsonBuilder;)Lcom/google/gson/Gson;
        33: areturn

  private static org.springframework.boot.autoconfigure.gson.GsonAutoConfiguration$StandardGsonBuilderCustomizer init_standardGsonBuilderCustomizer(org.springframework.beans.factory.BeanFactory);
    descriptor: (Lorg/springframework/beans/factory/BeanFactory;)Lorg/springframework/boot/autoconfigure/gson/GsonAutoConfiguration$StandardGsonBuilderCustomizer;
    flags: ACC_PRIVATE, ACC_STATIC
    Code:
      stack=3, locals=1, args_size=1
         0: getstatic     #18                 // Field java/lang/System.out:Ljava/io/PrintStream;
         3: ldc           #171                // String :debug: execution of lambda for standardGsonBuilderCustomizer
         5: invokevirtual #26                 // Method java/io/PrintStream.println:(Ljava/lang/String;)V
         8: aload_0
         9: ldc           #68                 // class org/springframework/boot/autoconfigure/gson/GsonAutoConfiguration
        11: invokeinterface #138,  2          // InterfaceMethod org/springframework/beans/factory/BeanFactory.getBean:(Ljava/lang/Class;)Ljava/lang/Object;
        16: checkcast     #68                 // class org/springframework/boot/autoconfigure/gson/GsonAutoConfiguration
        19: aload_0
        20: ldc           #40                 // class org/springframework/boot/autoconfigure/gson/GsonProperties
        22: invokeinterface #138,  2          // InterfaceMethod org/springframework/beans/factory/BeanFactory.getBean:(Ljava/lang/Class;)Ljava/lang/Object;
        27: checkcast     #40                 // class org/springframework/boot/autoconfigure/gson/GsonProperties
        30: invokevirtual #175                // Method org/springframework/boot/autoconfigure/gson/GsonAutoConfiguration.standardGsonBuilderCustomizer:(Lorg/springframework/boot/autoconfigure/gson/GsonProperties;)Lorg/springframework/boot/autoconfigure/gson/GsonAutoConfiguration$StandardGsonBuilderCustomizer;
        33: areturn
}
Signature: #3                           // Ljava/lang/Object;Lorg/springframework/context/ApplicationContextInitializer<Lorg/springframework/context/support/GenericApplicationContext;>;
RuntimeVisibleAnnotations:
  0: #8(#9=[c#10])
BootstrapMethods:
  0: #56 invokestatic java/lang/invoke/LambdaMetafactory.metafactory:(Ljava/lang/invoke/MethodHandles$Lookup;Ljava/lang/String;Ljava/lang/invoke/MethodType;Ljava/lang/invoke/MethodType;Ljava/lang/invoke/MethodHandle;Ljava/lang/invoke/MethodType;)Ljava/lang/invoke/CallSite;
    Method arguments:
      #42 ()Ljava/lang/Object;
      #47 invokestatic org/springframework/boot/autoconfigure/gson/GsonAutoConfigurationModule$Initializer.init_GsonProperties:(Lorg/springframework/beans/factory/BeanFactory;)Lorg/springframework/boot/autoconfigure/gson/GsonProperties;
      #49 ()Lorg/springframework/boot/autoconfigure/gson/GsonProperties;
  1: #56 invokestatic java/lang/invoke/LambdaMetafactory.metafactory:(Ljava/lang/invoke/MethodHandles$Lookup;Ljava/lang/String;Ljava/lang/invoke/MethodType;Ljava/lang/invoke/MethodType;Ljava/lang/invoke/MethodHandle;Ljava/lang/invoke/MethodType;)Ljava/lang/invoke/CallSite;
    Method arguments:
      #42 ()Ljava/lang/Object;
      #88 invokestatic org/springframework/boot/autoconfigure/gson/GsonAutoConfigurationModule$Initializer.init_gsonBuilder:(Lorg/springframework/beans/factory/BeanFactory;)Lcom/google/gson/GsonBuilder;
      #90 ()Lcom/google/gson/GsonBuilder;
  2: #56 invokestatic java/lang/invoke/LambdaMetafactory.metafactory:(Ljava/lang/invoke/MethodHandles$Lookup;Ljava/lang/String;Ljava/lang/invoke/MethodType;Ljava/lang/invoke/MethodType;Ljava/lang/invoke/MethodHandle;Ljava/lang/invoke/MethodType;)Ljava/lang/invoke/CallSite;
    Method arguments:
      #42 ()Ljava/lang/Object;
      #102 invokestatic org/springframework/boot/autoconfigure/gson/GsonAutoConfigurationModule$Initializer.init_gson:(Lorg/springframework/beans/factory/BeanFactory;)Lcom/google/gson/Gson;
      #104 ()Lcom/google/gson/Gson;
  3: #56 invokestatic java/lang/invoke/LambdaMetafactory.metafactory:(Ljava/lang/invoke/MethodHandles$Lookup;Ljava/lang/String;Ljava/lang/invoke/MethodType;Ljava/lang/invoke/MethodType;Ljava/lang/invoke/MethodHandle;Ljava/lang/invoke/MethodType;)Ljava/lang/invoke/CallSite;
    Method arguments:
      #42 ()Ljava/lang/Object;
      #116 invokestatic org/springframework/boot/autoconfigure/gson/GsonAutoConfigurationModule$Initializer.init_standardGsonBuilderCustomizer:(Lorg/springframework/beans/factory/BeanFactory;)Lorg/springframework/boot/autoconfigure/gson/GsonAutoConfiguration$StandardGsonBuilderCustomizer;
      #118 ()Lorg/springframework/boot/autoconfigure/gson/GsonAutoConfiguration$StandardGsonBuilderCustomizer;
