Classfile /Users/aclement/forks/spring-init-experiment/modules/library/target/classes/boot/autoconfigure/gson/GsonAutoConfigurationModule$Initializer.class
  Last modified Oct 12, 2018; size 5092 bytes
  MD5 checksum 34a972e3e544bf2f6d2d02df8dfcbe3e
  Compiled from "GsonAutoConfigurationModule.java"
class boot.autoconfigure.gson.GsonAutoConfigurationModule$Initializer extends java.lang.Object implements org.springframework.context.ApplicationContextInitializer<org.springframework.context.support.GenericApplicationContext>
  minor version: 0
  major version: 52
  flags: ACC_SUPER
Constant pool:
    #1 = Class              #2            // boot/autoconfigure/gson/GsonAutoConfigurationModule$Initializer
    #2 = Utf8               boot/autoconfigure/gson/GsonAutoConfigurationModule$Initializer
    #3 = Class              #4            // java/lang/Object
    #4 = Utf8               java/lang/Object
    #5 = Class              #6            // org/springframework/context/ApplicationContextInitializer
    #6 = Utf8               org/springframework/context/ApplicationContextInitializer
    #7 = Utf8               <init>
    #8 = Utf8               ()V
    #9 = Utf8               Code
   #10 = Methodref          #3.#11        // java/lang/Object."<init>":()V
   #11 = NameAndType        #7:#8         // "<init>":()V
   #12 = Utf8               LineNumberTable
   #13 = Utf8               LocalVariableTable
   #14 = Utf8               this
   #15 = Utf8               Lboot/autoconfigure/gson/GsonAutoConfigurationModule$Initializer;
   #16 = Utf8               initialize
   #17 = Utf8               (Lorg/springframework/context/support/GenericApplicationContext;)V
   #18 = Methodref          #19.#21       // org/springframework/context/support/GenericApplicationContext.getBeanFactory:()Lorg/springframework/beans/factory/config/ConfigurableListableBeanFactory;
   #19 = Class              #20           // org/springframework/context/support/GenericApplicationContext
   #20 = Utf8               org/springframework/context/support/GenericApplicationContext
   #21 = NameAndType        #22:#23       // getBeanFactory:()Lorg/springframework/beans/factory/config/ConfigurableListableBeanFactory;
   #22 = Utf8               getBeanFactory
   #23 = Utf8               ()Lorg/springframework/beans/factory/config/ConfigurableListableBeanFactory;
   #24 = Class              #25           // slim/ConditionService
   #25 = Utf8               slim/ConditionService
   #26 = InterfaceMethodref #27.#29       // org/springframework/beans/factory/config/ConfigurableListableBeanFactory.getBean:(Ljava/lang/Class;)Ljava/lang/Object;
   #27 = Class              #28           // org/springframework/beans/factory/config/ConfigurableListableBeanFactory
   #28 = Utf8               org/springframework/beans/factory/config/ConfigurableListableBeanFactory
   #29 = NameAndType        #30:#31       // getBean:(Ljava/lang/Class;)Ljava/lang/Object;
   #30 = Utf8               getBean
   #31 = Utf8               (Ljava/lang/Class;)Ljava/lang/Object;
   #32 = Class              #33           // org/springframework/boot/autoconfigure/gson/GsonAutoConfiguration
   #33 = Utf8               org/springframework/boot/autoconfigure/gson/GsonAutoConfiguration
   #34 = InterfaceMethodref #24.#35       // slim/ConditionService.matches:(Ljava/lang/Class;)Z
   #35 = NameAndType        #36:#37       // matches:(Ljava/lang/Class;)Z
   #36 = Utf8               matches
   #37 = Utf8               (Ljava/lang/Class;)Z
   #38 = Class              #39           // org/springframework/boot/autoconfigure/gson/GsonProperties
   #39 = Utf8               org/springframework/boot/autoconfigure/gson/GsonProperties
   #40 = InvokeDynamic      #0:#41        // #0:get:()Ljava/util/function/Supplier;
   #41 = NameAndType        #42:#43       // get:()Ljava/util/function/Supplier;
   #42 = Utf8               get
   #43 = Utf8               ()Ljava/util/function/Supplier;
   #44 = Class              #45           // org/springframework/beans/factory/config/BeanDefinitionCustomizer
   #45 = Utf8               org/springframework/beans/factory/config/BeanDefinitionCustomizer
   #46 = Methodref          #19.#47       // org/springframework/context/support/GenericApplicationContext.registerBean:(Ljava/lang/Class;Ljava/util/function/Supplier;[Lorg/springframework/beans/factory/config/BeanDefinitionCustomizer;)V
   #47 = NameAndType        #48:#49       // registerBean:(Ljava/lang/Class;Ljava/util/function/Supplier;[Lorg/springframework/beans/factory/config/BeanDefinitionCustomizer;)V
   #48 = Utf8               registerBean
   #49 = Utf8               (Ljava/lang/Class;Ljava/util/function/Supplier;[Lorg/springframework/beans/factory/config/BeanDefinitionCustomizer;)V
   #50 = Methodref          #19.#51       // org/springframework/context/support/GenericApplicationContext.registerBean:(Ljava/lang/Class;[Lorg/springframework/beans/factory/config/BeanDefinitionCustomizer;)V
   #51 = NameAndType        #48:#52       // registerBean:(Ljava/lang/Class;[Lorg/springframework/beans/factory/config/BeanDefinitionCustomizer;)V
   #52 = Utf8               (Ljava/lang/Class;[Lorg/springframework/beans/factory/config/BeanDefinitionCustomizer;)V
   #53 = Class              #54           // com/google/gson/GsonBuilder
   #54 = Utf8               com/google/gson/GsonBuilder
   #55 = InterfaceMethodref #24.#56       // slim/ConditionService.matches:(Ljava/lang/Class;Ljava/lang/Class;)Z
   #56 = NameAndType        #36:#57       // matches:(Ljava/lang/Class;Ljava/lang/Class;)Z
   #57 = Utf8               (Ljava/lang/Class;Ljava/lang/Class;)Z
   #58 = String             #59           // gsonBuilder
   #59 = Utf8               gsonBuilder
   #60 = InvokeDynamic      #1:#61        // #1:get:(Lorg/springframework/context/support/GenericApplicationContext;)Ljava/util/function/Supplier;
   #61 = NameAndType        #42:#62       // get:(Lorg/springframework/context/support/GenericApplicationContext;)Ljava/util/function/Supplier;
   #62 = Utf8               (Lorg/springframework/context/support/GenericApplicationContext;)Ljava/util/function/Supplier;
   #63 = Methodref          #19.#64       // org/springframework/context/support/GenericApplicationContext.registerBean:(Ljava/lang/String;Ljava/lang/Class;Ljava/util/function/Supplier;[Lorg/springframework/beans/factory/config/BeanDefinitionCustomizer;)V
   #64 = NameAndType        #48:#65       // registerBean:(Ljava/lang/String;Ljava/lang/Class;Ljava/util/function/Supplier;[Lorg/springframework/beans/factory/config/BeanDefinitionCustomizer;)V
   #65 = Utf8               (Ljava/lang/String;Ljava/lang/Class;Ljava/util/function/Supplier;[Lorg/springframework/beans/factory/config/BeanDefinitionCustomizer;)V
   #66 = Class              #67           // com/google/gson/Gson
   #67 = Utf8               com/google/gson/Gson
   #68 = String             #69           // gson
   #69 = Utf8               gson
   #70 = InvokeDynamic      #2:#61        // #2:get:(Lorg/springframework/context/support/GenericApplicationContext;)Ljava/util/function/Supplier;
   #71 = String             #72           // standardGsonBuilderCustomizer
   #72 = Utf8               standardGsonBuilderCustomizer
   #73 = Class              #74           // org/springframework/boot/autoconfigure/gson/GsonBuilderCustomizer
   #74 = Utf8               org/springframework/boot/autoconfigure/gson/GsonBuilderCustomizer
   #75 = InvokeDynamic      #3:#61        // #3:get:(Lorg/springframework/context/support/GenericApplicationContext;)Ljava/util/function/Supplier;
   #76 = Utf8               context
   #77 = Utf8               Lorg/springframework/context/support/GenericApplicationContext;
   #78 = Utf8               conditions
   #79 = Utf8               Lslim/ConditionService;
   #80 = Utf8               StackMapTable
   #81 = Utf8               MethodParameters
   #82 = Utf8               (Lorg/springframework/context/ConfigurableApplicationContext;)V
   #83 = Methodref          #1.#84        // boot/autoconfigure/gson/GsonAutoConfigurationModule$Initializer.initialize:(Lorg/springframework/context/support/GenericApplicationContext;)V
   #84 = NameAndType        #16:#17       // initialize:(Lorg/springframework/context/support/GenericApplicationContext;)V
   #85 = Utf8               (Lboot/autoconfigure/gson/GsonAutoConfigurationModule$Initializer;)V
   #86 = Methodref          #1.#11        // boot/autoconfigure/gson/GsonAutoConfigurationModule$Initializer."<init>":()V
   #87 = Utf8               lambda$0
   #88 = Utf8               ()Lorg/springframework/boot/autoconfigure/gson/GsonProperties;
   #89 = Methodref          #38.#11       // org/springframework/boot/autoconfigure/gson/GsonProperties."<init>":()V
   #90 = Utf8               lambda$1
   #91 = Utf8               (Lorg/springframework/context/support/GenericApplicationContext;)Lcom/google/gson/GsonBuilder;
   #92 = Methodref          #19.#29       // org/springframework/context/support/GenericApplicationContext.getBean:(Ljava/lang/Class;)Ljava/lang/Object;
   #93 = Class              #94           // java/util/ArrayList
   #94 = Utf8               java/util/ArrayList
   #95 = Methodref          #19.#96       // org/springframework/context/support/GenericApplicationContext.getBeansOfType:(Ljava/lang/Class;)Ljava/util/Map;
   #96 = NameAndType        #97:#98       // getBeansOfType:(Ljava/lang/Class;)Ljava/util/Map;
   #97 = Utf8               getBeansOfType
   #98 = Utf8               (Ljava/lang/Class;)Ljava/util/Map;
   #99 = InterfaceMethodref #100.#102     // java/util/Map.values:()Ljava/util/Collection;
  #100 = Class              #101          // java/util/Map
  #101 = Utf8               java/util/Map
  #102 = NameAndType        #103:#104     // values:()Ljava/util/Collection;
  #103 = Utf8               values
  #104 = Utf8               ()Ljava/util/Collection;
  #105 = Methodref          #93.#106      // java/util/ArrayList."<init>":(Ljava/util/Collection;)V
  #106 = NameAndType        #7:#107       // "<init>":(Ljava/util/Collection;)V
  #107 = Utf8               (Ljava/util/Collection;)V
  #108 = Methodref          #32.#109      // org/springframework/boot/autoconfigure/gson/GsonAutoConfiguration.gsonBuilder:(Ljava/util/List;)Lcom/google/gson/GsonBuilder;
  #109 = NameAndType        #59:#110      // gsonBuilder:(Ljava/util/List;)Lcom/google/gson/GsonBuilder;
  #110 = Utf8               (Ljava/util/List;)Lcom/google/gson/GsonBuilder;
  #111 = Utf8               lambda$2
  #112 = Utf8               (Lorg/springframework/context/support/GenericApplicationContext;)Lcom/google/gson/Gson;
  #113 = Methodref          #32.#114      // org/springframework/boot/autoconfigure/gson/GsonAutoConfiguration.gson:(Lcom/google/gson/GsonBuilder;)Lcom/google/gson/Gson;
  #114 = NameAndType        #69:#115      // gson:(Lcom/google/gson/GsonBuilder;)Lcom/google/gson/Gson;
  #115 = Utf8               (Lcom/google/gson/GsonBuilder;)Lcom/google/gson/Gson;
  #116 = Utf8               lambda$3
  #117 = Utf8               (Lorg/springframework/context/support/GenericApplicationContext;)Lorg/springframework/boot/autoconfigure/gson/GsonBuilderCustomizer;
  #118 = Methodref          #32.#119      // org/springframework/boot/autoconfigure/gson/GsonAutoConfiguration.standardGsonBuilderCustomizer:(Lorg/springframework/boot/autoconfigure/gson/GsonProperties;)Lorg/springframework/boot/autoconfigure/gson/GsonAutoConfiguration$StandardGsonBuilderCustomizer;
  #119 = NameAndType        #72:#120      // standardGsonBuilderCustomizer:(Lorg/springframework/boot/autoconfigure/gson/GsonProperties;)Lorg/springframework/boot/autoconfigure/gson/GsonAutoConfiguration$StandardGsonBuilderCustomizer;
  #120 = Utf8               (Lorg/springframework/boot/autoconfigure/gson/GsonProperties;)Lorg/springframework/boot/autoconfigure/gson/GsonAutoConfiguration$StandardGsonBuilderCustomizer;
  #121 = Utf8               SourceFile
  #122 = Utf8               GsonAutoConfigurationModule.java
  #123 = Utf8               Signature
  #124 = Utf8               Ljava/lang/Object;Lorg/springframework/context/ApplicationContextInitializer<Lorg/springframework/context/support/GenericApplicationContext;>;
  #125 = Utf8               RuntimeVisibleAnnotations
  #126 = Utf8               Lslim/InitializerMapping;
  #127 = Utf8               value
  #128 = Utf8               Lorg/springframework/boot/autoconfigure/gson/GsonAutoConfiguration;
  #129 = Utf8               BootstrapMethods
  #130 = Methodref          #131.#133     // java/lang/invoke/LambdaMetafactory.metafactory:(Ljava/lang/invoke/MethodHandles$Lookup;Ljava/lang/String;Ljava/lang/invoke/MethodType;Ljava/lang/invoke/MethodType;Ljava/lang/invoke/MethodHandle;Ljava/lang/invoke/MethodType;)Ljava/lang/invoke/CallSite;
  #131 = Class              #132          // java/lang/invoke/LambdaMetafactory
  #132 = Utf8               java/lang/invoke/LambdaMetafactory
  #133 = NameAndType        #134:#135     // metafactory:(Ljava/lang/invoke/MethodHandles$Lookup;Ljava/lang/String;Ljava/lang/invoke/MethodType;Ljava/lang/invoke/MethodType;Ljava/lang/invoke/MethodHandle;Ljava/lang/invoke/MethodType;)Ljava/lang/invoke/CallSite;
  #134 = Utf8               metafactory
  #135 = Utf8               (Ljava/lang/invoke/MethodHandles$Lookup;Ljava/lang/String;Ljava/lang/invoke/MethodType;Ljava/lang/invoke/MethodType;Ljava/lang/invoke/MethodHandle;Ljava/lang/invoke/MethodType;)Ljava/lang/invoke/CallSite;
  #136 = MethodHandle       #6:#130       // invokestatic java/lang/invoke/LambdaMetafactory.metafactory:(Ljava/lang/invoke/MethodHandles$Lookup;Ljava/lang/String;Ljava/lang/invoke/MethodType;Ljava/lang/invoke/MethodType;Ljava/lang/invoke/MethodHandle;Ljava/lang/invoke/MethodType;)Ljava/lang/invoke/CallSite;
  #137 = Utf8               ()Ljava/lang/Object;
  #138 = MethodType         #137          //  ()Ljava/lang/Object;
  #139 = Methodref          #1.#140       // boot/autoconfigure/gson/GsonAutoConfigurationModule$Initializer.lambda$0:()Lorg/springframework/boot/autoconfigure/gson/GsonProperties;
  #140 = NameAndType        #87:#88       // lambda$0:()Lorg/springframework/boot/autoconfigure/gson/GsonProperties;
  #141 = MethodHandle       #6:#139       // invokestatic boot/autoconfigure/gson/GsonAutoConfigurationModule$Initializer.lambda$0:()Lorg/springframework/boot/autoconfigure/gson/GsonProperties;
  #142 = MethodType         #88           //  ()Lorg/springframework/boot/autoconfigure/gson/GsonProperties;
  #143 = MethodType         #137          //  ()Ljava/lang/Object;
  #144 = Methodref          #1.#145       // boot/autoconfigure/gson/GsonAutoConfigurationModule$Initializer.lambda$1:(Lorg/springframework/context/support/GenericApplicationContext;)Lcom/google/gson/GsonBuilder;
  #145 = NameAndType        #90:#91       // lambda$1:(Lorg/springframework/context/support/GenericApplicationContext;)Lcom/google/gson/GsonBuilder;
  #146 = MethodHandle       #6:#144       // invokestatic boot/autoconfigure/gson/GsonAutoConfigurationModule$Initializer.lambda$1:(Lorg/springframework/context/support/GenericApplicationContext;)Lcom/google/gson/GsonBuilder;
  #147 = Utf8               ()Lcom/google/gson/GsonBuilder;
  #148 = MethodType         #147          //  ()Lcom/google/gson/GsonBuilder;
  #149 = MethodType         #137          //  ()Ljava/lang/Object;
  #150 = Methodref          #1.#151       // boot/autoconfigure/gson/GsonAutoConfigurationModule$Initializer.lambda$2:(Lorg/springframework/context/support/GenericApplicationContext;)Lcom/google/gson/Gson;
  #151 = NameAndType        #111:#112     // lambda$2:(Lorg/springframework/context/support/GenericApplicationContext;)Lcom/google/gson/Gson;
  #152 = MethodHandle       #6:#150       // invokestatic boot/autoconfigure/gson/GsonAutoConfigurationModule$Initializer.lambda$2:(Lorg/springframework/context/support/GenericApplicationContext;)Lcom/google/gson/Gson;
  #153 = Utf8               ()Lcom/google/gson/Gson;
  #154 = MethodType         #153          //  ()Lcom/google/gson/Gson;
  #155 = MethodType         #137          //  ()Ljava/lang/Object;
  #156 = Methodref          #1.#157       // boot/autoconfigure/gson/GsonAutoConfigurationModule$Initializer.lambda$3:(Lorg/springframework/context/support/GenericApplicationContext;)Lorg/springframework/boot/autoconfigure/gson/GsonBuilderCustomizer;
  #157 = NameAndType        #116:#117     // lambda$3:(Lorg/springframework/context/support/GenericApplicationContext;)Lorg/springframework/boot/autoconfigure/gson/GsonBuilderCustomizer;
  #158 = MethodHandle       #6:#156       // invokestatic boot/autoconfigure/gson/GsonAutoConfigurationModule$Initializer.lambda$3:(Lorg/springframework/context/support/GenericApplicationContext;)Lorg/springframework/boot/autoconfigure/gson/GsonBuilderCustomizer;
  #159 = Utf8               ()Lorg/springframework/boot/autoconfigure/gson/GsonBuilderCustomizer;
  #160 = MethodType         #159          //  ()Lorg/springframework/boot/autoconfigure/gson/GsonBuilderCustomizer;
  #161 = Utf8               InnerClasses
  #162 = Class              #163          // boot/autoconfigure/gson/GsonAutoConfigurationModule
  #163 = Utf8               boot/autoconfigure/gson/GsonAutoConfigurationModule
  #164 = Utf8               Initializer
  #165 = Class              #166          // java/lang/invoke/MethodHandles$Lookup
  #166 = Utf8               java/lang/invoke/MethodHandles$Lookup
  #167 = Class              #168          // java/lang/invoke/MethodHandles
  #168 = Utf8               java/lang/invoke/MethodHandles
  #169 = Utf8               Lookup
  #170 = Class              #171          // org/springframework/boot/autoconfigure/gson/GsonAutoConfiguration$StandardGsonBuilderCustomizer
  #171 = Utf8               org/springframework/boot/autoconfigure/gson/GsonAutoConfiguration$StandardGsonBuilderCustomizer
  #172 = Utf8               StandardGsonBuilderCustomizer
{
  private boot.autoconfigure.gson.GsonAutoConfigurationModule$Initializer();
    descriptor: ()V
    flags: ACC_PRIVATE
    Code:
      stack=1, locals=1, args_size=1
         0: aload_0
         1: invokespecial #10                 // Method java/lang/Object."<init>":()V
         4: return

  public void initialize(org.springframework.context.support.GenericApplicationContext);
    descriptor: (Lorg/springframework/context/support/GenericApplicationContext;)V
    flags: ACC_PUBLIC
    Code:
      stack=5, locals=3, args_size=2
         0: aload_1
         1: invokevirtual #18                 // Method org/springframework/context/support/GenericApplicationContext.getBeanFactory:()Lorg/springframework/beans/factory/config/ConfigurableListableBeanFactory;
         4: ldc           #24                 // class slim/ConditionService
         6: invokeinterface #26,  2           // InterfaceMethod org/springframework/beans/factory/config/ConfigurableListableBeanFactory.getBean:(Ljava/lang/Class;)Ljava/lang/Object;
        11: checkcast     #24                 // class slim/ConditionService
        14: astore_2
        15: aload_2
        16: ldc           #32                 // class org/springframework/boot/autoconfigure/gson/GsonAutoConfiguration
        18: invokeinterface #34,  2           // InterfaceMethod slim/ConditionService.matches:(Ljava/lang/Class;)Z
        23: ifeq          131
        26: aload_1
        27: ldc           #38                 // class org/springframework/boot/autoconfigure/gson/GsonProperties
        29: invokedynamic #40,  0             // InvokeDynamic #0:get:()Ljava/util/function/Supplier;
        34: iconst_0
        35: anewarray     #44                 // class org/springframework/beans/factory/config/BeanDefinitionCustomizer
        38: invokevirtual #46                 // Method org/springframework/context/support/GenericApplicationContext.registerBean:(Ljava/lang/Class;Ljava/util/function/Supplier;[Lorg/springframework/beans/factory/config/BeanDefinitionCustomizer;)V
        41: aload_1
        42: ldc           #32                 // class org/springframework/boot/autoconfigure/gson/GsonAutoConfiguration
        44: iconst_0
        45: anewarray     #44                 // class org/springframework/beans/factory/config/BeanDefinitionCustomizer
        48: invokevirtual #50                 // Method org/springframework/context/support/GenericApplicationContext.registerBean:(Ljava/lang/Class;[Lorg/springframework/beans/factory/config/BeanDefinitionCustomizer;)V
        51: aload_2
        52: ldc           #32                 // class org/springframework/boot/autoconfigure/gson/GsonAutoConfiguration
        54: ldc           #53                 // class com/google/gson/GsonBuilder
        56: invokeinterface #55,  3           // InterfaceMethod slim/ConditionService.matches:(Ljava/lang/Class;Ljava/lang/Class;)Z
        61: ifeq          82
        64: aload_1
        65: ldc           #58                 // String gsonBuilder
        67: ldc           #53                 // class com/google/gson/GsonBuilder
        69: aload_1
        70: invokedynamic #60,  0             // InvokeDynamic #1:get:(Lorg/springframework/context/support/GenericApplicationContext;)Ljava/util/function/Supplier;
        75: iconst_0
        76: anewarray     #44                 // class org/springframework/beans/factory/config/BeanDefinitionCustomizer
        79: invokevirtual #63                 // Method org/springframework/context/support/GenericApplicationContext.registerBean:(Ljava/lang/String;Ljava/lang/Class;Ljava/util/function/Supplier;[Lorg/springframework/beans/factory/config/BeanDefinitionCustomizer;)V
        82: aload_2
        83: ldc           #32                 // class org/springframework/boot/autoconfigure/gson/GsonAutoConfiguration
        85: ldc           #66                 // class com/google/gson/Gson
        87: invokeinterface #55,  3           // InterfaceMethod slim/ConditionService.matches:(Ljava/lang/Class;Ljava/lang/Class;)Z
        92: ifeq          113
        95: aload_1
        96: ldc           #68                 // String gson
        98: ldc           #66                 // class com/google/gson/Gson
       100: aload_1
       101: invokedynamic #70,  0             // InvokeDynamic #2:get:(Lorg/springframework/context/support/GenericApplicationContext;)Ljava/util/function/Supplier;
       106: iconst_0
       107: anewarray     #44                 // class org/springframework/beans/factory/config/BeanDefinitionCustomizer
       110: invokevirtual #63                 // Method org/springframework/context/support/GenericApplicationContext.registerBean:(Ljava/lang/String;Ljava/lang/Class;Ljava/util/function/Supplier;[Lorg/springframework/beans/factory/config/BeanDefinitionCustomizer;)V
       113: aload_1
       114: ldc           #71                 // String standardGsonBuilderCustomizer
       116: ldc           #73                 // class org/springframework/boot/autoconfigure/gson/GsonBuilderCustomizer
       118: aload_1
       119: invokedynamic #75,  0             // InvokeDynamic #3:get:(Lorg/springframework/context/support/GenericApplicationContext;)Ljava/util/function/Supplier;
       124: iconst_0
       125: anewarray     #44                 // class org/springframework/beans/factory/config/BeanDefinitionCustomizer
       128: invokevirtual #63                 // Method org/springframework/context/support/GenericApplicationContext.registerBean:(Ljava/lang/String;Ljava/lang/Class;Ljava/util/function/Supplier;[Lorg/springframework/beans/factory/config/BeanDefinitionCustomizer;)V
       131: return

  public void initialize(org.springframework.context.ConfigurableApplicationContext);
    descriptor: (Lorg/springframework/context/ConfigurableApplicationContext;)V
    flags: ACC_PUBLIC, ACC_BRIDGE, ACC_SYNTHETIC
    Code:
      stack=2, locals=2, args_size=2
         0: aload_0
         1: aload_1
         2: checkcast     #19                 // class org/springframework/context/support/GenericApplicationContext
         5: invokevirtual #83                 // Method initialize:(Lorg/springframework/context/support/GenericApplicationContext;)V
         8: return

  boot.autoconfigure.gson.GsonAutoConfigurationModule$Initializer(boot.autoconfigure.gson.GsonAutoConfigurationModule$Initializer);
    descriptor: (Lboot/autoconfigure/gson/GsonAutoConfigurationModule$Initializer;)V
    flags: ACC_SYNTHETIC
    Code:
      stack=1, locals=2, args_size=2
         0: aload_0
         1: invokespecial #86                 // Method "<init>":()V
         4: return

  private static org.springframework.boot.autoconfigure.gson.GsonProperties lambda$0();
    descriptor: ()Lorg/springframework/boot/autoconfigure/gson/GsonProperties;
    flags: ACC_PRIVATE, ACC_STATIC, ACC_SYNTHETIC
    Code:
      stack=2, locals=0, args_size=0
         0: new           #38                 // class org/springframework/boot/autoconfigure/gson/GsonProperties
         3: dup
         4: invokespecial #89                 // Method org/springframework/boot/autoconfigure/gson/GsonProperties."<init>":()V
         7: areturn
      LineNumberTable:
        line 67: 0
      LocalVariableTable:
        Start  Length  Slot  Name   Signature

  private static com.google.gson.Gson lambda$2(org.springframework.context.support.GenericApplicationContext);
    descriptor: (Lorg/springframework/context/support/GenericApplicationContext;)Lcom/google/gson/Gson;
    flags: ACC_PRIVATE, ACC_STATIC, ACC_SYNTHETIC
    Code:
      stack=3, locals=1, args_size=1
         0: aload_0
         1: ldc           #32                 // class org/springframework/boot/autoconfigure/gson/GsonAutoConfiguration
         3: invokevirtual #92                 // Method org/springframework/context/support/GenericApplicationContext.getBean:(Ljava/lang/Class;)Ljava/lang/Object;
         6: checkcast     #32                 // class org/springframework/boot/autoconfigure/gson/GsonAutoConfiguration
         9: aload_0
        10: ldc           #53                 // class com/google/gson/GsonBuilder
        12: invokevirtual #92                 // Method org/springframework/context/support/GenericApplicationContext.getBean:(Ljava/lang/Class;)Ljava/lang/Object;
        15: checkcast     #53                 // class com/google/gson/GsonBuilder
        18: invokevirtual #113                // Method org/springframework/boot/autoconfigure/gson/GsonAutoConfiguration.gson:(Lcom/google/gson/GsonBuilder;)Lcom/google/gson/Gson;
        21: areturn
      LineNumberTable:
        line 78: 0
        line 79: 9
      LocalVariableTable:
        Start  Length  Slot  Name   Signature







  private static org.springframework.boot.autoconfigure.gson.GsonBuilderCustomizer lambda$3(org.springframework.context.support.GenericApplicationContext);
    descriptor: (Lorg/springframework/context/support/GenericApplicationContext;)Lorg/springframework/boot/autoconfigure/gson/GsonBuilderCustomizer;
    flags: ACC_PRIVATE, ACC_STATIC, ACC_SYNTHETIC
    Code:
      stack=3, locals=1, args_size=1
         0: aload_0
         1: ldc           #32                 // class org/springframework/boot/autoconfigure/gson/GsonAutoConfiguration
         3: invokevirtual #92                 // Method org/springframework/context/support/GenericApplicationContext.getBean:(Ljava/lang/Class;)Ljava/lang/Object;
         6: checkcast     #32                 // class org/springframework/boot/autoconfigure/gson/GsonAutoConfiguration
         9: aload_0
        10: ldc           #38                 // class org/springframework/boot/autoconfigure/gson/GsonProperties
        12: invokevirtual #92                 // Method org/springframework/context/support/GenericApplicationContext.getBean:(Ljava/lang/Class;)Ljava/lang/Object;
        15: checkcast     #38                 // class org/springframework/boot/autoconfigure/gson/GsonProperties
        18: invokevirtual #118                // Method org/springframework/boot/autoconfigure/gson/GsonAutoConfiguration.standardGsonBuilderCustomizer:(Lorg/springframework/boot/autoconfigure/gson/GsonProperties;)Lorg/springframework/boot/autoconfigure/gson/GsonAutoConfiguration$StandardGsonBuilderCustomizer;
        21: areturn
        
        
        
        
        
        
     
  private static com.google.gson.GsonBuilder lambda$1(org.springframework.context.support.GenericApplicationContext);
    descriptor: (Lorg/springframework/context/support/GenericApplicationContext;)Lcom/google/gson/GsonBuilder;
    flags: ACC_PRIVATE, ACC_STATIC, ACC_SYNTHETIC
    Code:
      stack=5, locals=1, args_size=1
         0: aload_0
         1: ldc           #32                 // class org/springframework/boot/autoconfigure/gson/GsonAutoConfiguration
         3: invokevirtual #92                 // Method org/springframework/context/support/GenericApplicationContext.getBean:(Ljava/lang/Class;)Ljava/lang/Object;
         6: checkcast     #32                 // class org/springframework/boot/autoconfigure/gson/GsonAutoConfiguration
         9: new           #93                 // class java/util/ArrayList
        12: dup
        13: aload_0
        14: ldc           #73                 // class org/springframework/boot/autoconfigure/gson/GsonBuilderCustomizer
        16: invokevirtual #95                 // Method org/springframework/context/support/GenericApplicationContext.getBeansOfType:(Ljava/lang/Class;)Ljava/util/Map;
        19: invokeinterface #99,  1           // InterfaceMethod java/util/Map.values:()Ljava/util/Collection;
        24: invokespecial #105                // Method java/util/ArrayList."<init>":(Ljava/util/Collection;)V
        27: invokevirtual #108                // Method org/springframework/boot/autoconfigure/gson/GsonAutoConfiguration.gsonBuilder:(Ljava/util/List;)Lcom/google/gson/GsonBuilder;
        30: areturn
}
SourceFile: "GsonAutoConfigurationModule.java"
Signature: #124                         // Ljava/lang/Object;Lorg/springframework/context/ApplicationContextInitializer<Lorg/springframework/context/support/GenericApplicationContext;>;
RuntimeVisibleAnnotations:
  0: #126(#127=[c#128])
BootstrapMethods:
  0: #136 invokestatic java/lang/invoke/LambdaMetafactory.metafactory:(Ljava/lang/invoke/MethodHandles$Lookup;Ljava/lang/String;Ljava/lang/invoke/MethodType;Ljava/lang/invoke/MethodType;Ljava/lang/invoke/MethodHandle;Ljava/lang/invoke/MethodType;)Ljava/lang/invoke/CallSite;
    Method arguments:
      #138 ()Ljava/lang/Object;
      #141 invokestatic boot/autoconfigure/gson/GsonAutoConfigurationModule$Initializer.lambda$0:()Lorg/springframework/boot/autoconfigure/gson/GsonProperties;
      #142 ()Lorg/springframework/boot/autoconfigure/gson/GsonProperties;
  1: #136 invokestatic java/lang/invoke/LambdaMetafactory.metafactory:(Ljava/lang/invoke/MethodHandles$Lookup;Ljava/lang/String;Ljava/lang/invoke/MethodType;Ljava/lang/invoke/MethodType;Ljava/lang/invoke/MethodHandle;Ljava/lang/invoke/MethodType;)Ljava/lang/invoke/CallSite;
    Method arguments:
      #143 ()Ljava/lang/Object;
      #146 invokestatic boot/autoconfigure/gson/GsonAutoConfigurationModule$Initializer.lambda$1:(Lorg/springframework/context/support/GenericApplicationContext;)Lcom/google/gson/GsonBuilder;
      #148 ()Lcom/google/gson/GsonBuilder;
  2: #136 invokestatic java/lang/invoke/LambdaMetafactory.metafactory:(Ljava/lang/invoke/MethodHandles$Lookup;Ljava/lang/String;Ljava/lang/invoke/MethodType;Ljava/lang/invoke/MethodType;Ljava/lang/invoke/MethodHandle;Ljava/lang/invoke/MethodType;)Ljava/lang/invoke/CallSite;
    Method arguments:
      #149 ()Ljava/lang/Object;
      #152 invokestatic boot/autoconfigure/gson/GsonAutoConfigurationModule$Initializer.lambda$2:(Lorg/springframework/context/support/GenericApplicationContext;)Lcom/google/gson/Gson;
      #154 ()Lcom/google/gson/Gson;
  3: #136 invokestatic java/lang/invoke/LambdaMetafactory.metafactory:(Ljava/lang/invoke/MethodHandles$Lookup;Ljava/lang/String;Ljava/lang/invoke/MethodType;Ljava/lang/invoke/MethodType;Ljava/lang/invoke/MethodHandle;Ljava/lang/invoke/MethodType;)Ljava/lang/invoke/CallSite;
    Method arguments:
      #155 ()Ljava/lang/Object;
      #158 invokestatic boot/autoconfigure/gson/GsonAutoConfigurationModule$Initializer.lambda$3:(Lorg/springframework/context/support/GenericApplicationContext;)Lorg/springframework/boot/autoconfigure/gson/GsonBuilderCustomizer;
      #160 ()Lorg/springframework/boot/autoconfigure/gson/GsonBuilderCustomizer;
InnerClasses:
     private static #164= #1 of #162; //Initializer=class boot/autoconfigure/gson/GsonAutoConfigurationModule$Initializer of class boot/autoconfigure/gson/GsonAutoConfigurationModule
     public static final #169= #165 of #167; //Lookup=class java/lang/invoke/MethodHandles$Lookup of class java/lang/invoke/MethodHandles
     static final #172= #170 of #32; //StandardGsonBuilderCustomizer=class org/springframework/boot/autoconfigure/gson/GsonAutoConfiguration$StandardGsonBuilderCustomizer of class org/springframework/boot/autoconfigure/gson/GsonAutoConfiguration

     
     