Classfile /Users/aclement/forks/spring-init-experiment/application/target/classes/org/springframework/boot/autoconfigure/gson/GsonAutoConfigurationModule.class
  Last modified 19-Oct-2018; size 1394 bytes
  MD5 checksum 5ecec3bc720c6998cfb75a96bb94240d
public class org.springframework.boot.autoconfigure.gson.GsonAutoConfigurationModule implements slim.Module
  minor version: 0
  major version: 52
  flags: ACC_PUBLIC, ACC_SUPER
Constant pool:
   #1 = Utf8               org/springframework/boot/autoconfigure/gson/GsonAutoConfigurationModule
   #2 = Class              #1             // org/springframework/boot/autoconfigure/gson/GsonAutoConfigurationModule
   #3 = Utf8               java/lang/Object
   #4 = Class              #3             // java/lang/Object
   #5 = Utf8               slim/Module
   #6 = Class              #5             // slim/Module
   #7 = Utf8               Lorg/springframework/context/annotation/Configuration;
   #8 = Utf8               value
   #9 = Utf8
  #10 = Utf8               Lorg/springframework/context/annotation/Import;
  #11 = Utf8               Lorg/springframework/boot/autoconfigure/gson/GsonAutoConfiguration;
  #12 = Utf8               Lslim/ImportModule;
  #13 = Utf8               module
  #14 = Utf8               Lboot/autoconfigure/context/ContextAutoConfigurationModule;
  #15 = Utf8               initializers
  #16 = Utf8               ()Ljava/util/List;
  #17 = Utf8               ()Ljava/util/List<Lorg/springframework/context/ApplicationContextInitializer<Lorg/springframework/context/support/GenericApplicationContext;>;>;
  #18 = Utf8               org/springframework/context/ApplicationContextInitializer
  #19 = Class              #18            // org/springframework/context/ApplicationContextInitializer
  #20 = Utf8               $$initializer
  #21 = Utf8               ()Lorg/springframework/context/ApplicationContextInitializer;
  #22 = NameAndType        #20:#21        // $$initializer:()Lorg/springframework/context/ApplicationContextInitializer;
  #23 = Methodref          #2.#22         // org/springframework/boot/autoconfigure/gson/GsonAutoConfigurationModule.$$initializer:()Lorg/springframework/context/ApplicationContextInitializer;
  #24 = Utf8               java/util/Arrays
  #25 = Class              #24            // java/util/Arrays
  #26 = Utf8               asList
  #27 = Utf8               ([Ljava/lang/Object;)Ljava/util/List;
  #28 = NameAndType        #26:#27        // asList:([Ljava/lang/Object;)Ljava/util/List;
  #29 = Methodref          #25.#28        // java/util/Arrays.asList:([Ljava/lang/Object;)Ljava/util/List;
  #30 = Utf8               ()Lorg/springframework/context/ApplicationContextInitializer<Lorg/springframework/context/support/GenericApplicationContext;>;
  #31 = Utf8               org/springframework/boot/autoconfigure/gson/GsonAutoConfigurationModule$Initializer
  #32 = Class              #31            // org/springframework/boot/autoconfigure/gson/GsonAutoConfigurationModule$Initializer
  #33 = Utf8               <init>
  #34 = Utf8               (Lorg/springframework/boot/autoconfigure/gson/GsonAutoConfigurationModule$Initializer;)V
  #35 = NameAndType        #33:#34        // "<init>":(Lorg/springframework/boot/autoconfigure/gson/GsonAutoConfigurationModule$Initializer;)V
  #36 = Methodref          #32.#35        // org/springframework/boot/autoconfigure/gson/GsonAutoConfigurationModule$Initializer."<init>":(Lorg/springframework/boot/autoconfigure/gson/GsonAutoConfigurationModule$Initializer;)V
  #37 = Utf8               ()V
  #38 = NameAndType        #33:#37        // "<init>":()V
  #39 = Methodref          #4.#38         // java/lang/Object."<init>":()V
  #40 = Utf8               Code
  #41 = Utf8               Signature
  #42 = Utf8               RuntimeVisibleAnnotations
{
  public java.util.List<org.springframework.context.ApplicationContextInitializer<org.springframework.context.support.GenericApplicationContext>> initializers();
    descriptor: ()Ljava/util/List;
    flags: ACC_PUBLIC
    Code:
      stack=4, locals=1, args_size=1
         0: iconst_1
         1: anewarray     #19                 // class org/springframework/context/ApplicationContextInitializer
         4: dup
         5: iconst_0
         6: invokestatic  #23                 // Method $$initializer:()Lorg/springframework/context/ApplicationContextInitializer;
         9: aastore
        10: invokestatic  #29                 // Method java/util/Arrays.asList:([Ljava/lang/Object;)Ljava/util/List;
        13: areturn
    Signature: #17                          // ()Ljava/util/List<Lorg/springframework/context/ApplicationContextInitializer<Lorg/springframework/context/support/GenericApplicationContext;>;>;

  public static org.springframework.context.ApplicationContextInitializer<org.springframework.context.support.GenericApplicationContext> $$initializer();
    descriptor: ()Lorg/springframework/context/ApplicationContextInitializer;
    flags: ACC_PUBLIC, ACC_STATIC
    Code:
      stack=3, locals=0, args_size=0
         0: new           #32                 // class org/springframework/boot/autoconfigure/gson/GsonAutoConfigurationModule$Initializer
         3: dup
         4: aconst_null
         5: invokespecial #36                 // Method org/springframework/boot/autoconfigure/gson/GsonAutoConfigurationModule$Initializer."<init>":(Lorg/springframework/boot/autoconfigure/gson/GsonAutoConfigurationModule$Initializer;)V
         8: areturn
    Signature: #30                          // ()Lorg/springframework/context/ApplicationContextInitializer<Lorg/springframework/context/support/GenericApplicationContext;>;

  public org.springframework.boot.autoconfigure.gson.GsonAutoConfigurationModule();
    descriptor: ()V
    flags: ACC_PUBLIC
    Code:
      stack=1, locals=1, args_size=1
         0: aload_0
         1: invokespecial #39                 // Method java/lang/Object."<init>":()V
         4: return
}
RuntimeVisibleAnnotations:
  0: #7(#8=s#9)
  1: #10(#8=[c#11])
  2: #12(#13=[c#14])
