boot.autoconfigure.mustache.MustacheAutoConfigurationModule
Class level annotations: 
  @org.springframework.context.annotation.Configuration
  @org.springframework.context.annotation.Import(value=[Lorg/springframework/boot/autoconfigure/mustache/MustacheAutoConfiguration;])
  @slim.ImportModule(module=[Lboot/autoconfigure/context/ContextAutoConfigurationModule;])


FIELDS

METHODS
public void <init>()
0:    aload_0
1:    invokespecial	java.lang.Object.<init> ()V (10)
4:    return

public java.util.List initializers() [Signature(()Ljava/util/List<Lorg/springframework/context/ApplicationContextInitializer<Lorg/springframework/context/support/GenericApplicationContext;>;>;)]
0:    iconst_2
1:    anewarray		<org.springframework.context.ApplicationContextInitializer> (20)
4:    dup
5:    iconst_0
6:    new		<boot.autoconfigure.mustache.MustacheAutoConfigurationModule$Initializer> (22)
9:    dup
10:   invokespecial	boot.autoconfigure.mustache.MustacheAutoConfigurationModule$Initializer.<init> ()V (24)
13:   aastore
14:   dup
15:   iconst_1
16:   invokestatic	boot.autoconfigure.mustache.MustacheReactiveWebConfigurationGenerated.initializer ()Lorg/springframework/context/ApplicationContextInitializer; (25)
19:   aastore
20:   invokestatic	java.util.Arrays.asList ([Ljava/lang/Object;)Ljava/util/List; (31)
23:   areturn

