org.springframework.boot.autoconfigure.mustache.MustacheAutoConfigurationModule$Initializer
Class level annotations: 
  @slim.InitializerMapping(value=[Lorg/springframework/boot/autoconfigure/mustache/MustacheAutoConfiguration;])


FIELDS

METHODS
private void <init>()
0:    aload_0
1:    dup
2:    invokespecial	java.lang.Object.<init> ()V (119)
5:    pop
6:    return

void <init>(org.springframework.boot.autoconfigure.mustache.MustacheAutoConfigurationModule$Initializer arg1)
0:    aload_0
1:    dup
2:    invokespecial	java.lang.Object.<init> ()V (119)
5:    pop
6:    return

public volatile void initialize(org.springframework.context.ConfigurableApplicationContext arg1)
0:    aload_0
1:    aload_1
2:    checkcast		<org.springframework.context.support.GenericApplicationContext> (62)
5:    invokevirtual	org.springframework.boot.autoconfigure.mustache.MustacheAutoConfigurationModule$Initializer.initialize (Lorg/springframework/context/support/GenericApplicationContext;)V (114)
8:    return

public void initialize(org.springframework.context.support.GenericApplicationContext arg1)
0:    getstatic		java.lang.System.out Ljava/io/PrintStream; (18)
3:    ldc		":debug: Processing type level conditions on org.springframework.boot.autoconfigure.mustache.MustacheAutoConfiguration" (20)
5:    invokevirtual	java.io.PrintStream.println (Ljava/lang/String;)V (26)
8:    ldc		"com.samskivert.mustache.Mustache" (28)
10:   aconst_null
11:   invokestatic	org.springframework.util.ClassUtils.isPresent (Ljava/lang/String;Ljava/lang/ClassLoader;)Z (34)
14:   ifeq		#147
17:   getstatic		java.lang.System.out Ljava/io/PrintStream; (18)
20:   ldc		":debug: Passed condition checks on org.springframework.boot.autoconfigure.mustache.MustacheAutoConfiguration" (36)
22:   invokevirtual	java.io.PrintStream.println (Ljava/lang/String;)V (26)
25:   iconst_0
26:   anewarray		<org.springframework.beans.factory.config.BeanDefinitionCustomizer> (38)
29:   astore_2
30:   aload_1
31:   ldc		org.springframework.boot.autoconfigure.mustache.MustacheProperties (40)
33:   aload_1
34:   invokedynamic	#0.get (Lorg/springframework/beans/factory/BeanFactory;)Ljava/util/function/Supplier; (60)
39:   iconst_0
40:   anewarray		<org.springframework.beans.factory.config.BeanDefinitionCustomizer> (38)
43:   invokevirtual	org.springframework.context.support.GenericApplicationContext.registerBean (Ljava/lang/Class;Ljava/util/function/Supplier;[Lorg/springframework/beans/factory/config/BeanDefinitionCustomizer;)V (66)
46:   aload_1
47:   ldc		org.springframework.boot.autoconfigure.mustache.MustacheAutoConfiguration (68)
49:   aload_2
50:   invokevirtual	org.springframework.context.support.GenericApplicationContext.registerBean (Ljava/lang/Class;[Lorg/springframework/beans/factory/config/BeanDefinitionCustomizer;)V (71)
53:   getstatic		java.lang.System.out Ljava/io/PrintStream; (18)
56:   ldc		":debug: Checking conditions before calling registerBean for bean factory method mustacheCompiler" (73)
58:   invokevirtual	java.io.PrintStream.println (Ljava/lang/String;)V (26)
61:   aload_1
62:   invokevirtual	org.springframework.context.support.GenericApplicationContext.getBeanFactory ()Lorg/springframework/beans/factory/config/ConfigurableListableBeanFactory; (77)
65:   ldc		com.samskivert.mustache.Mustache$Compiler (79)
67:   invokeinterface	org.springframework.beans.factory.ListableBeanFactory.getBeanNamesForType (Ljava/lang/Class;)[Ljava/lang/String; (85)	2	0
72:   arraylength
73:   ifne		#100
76:   getstatic		java.lang.System.out Ljava/io/PrintStream; (18)
79:   ldc		":debug: Calling registerBean for bean factory method mustacheCompiler" (87)
81:   invokevirtual	java.io.PrintStream.println (Ljava/lang/String;)V (26)
84:   aload_1
85:   ldc		com.samskivert.mustache.Mustache$Compiler (79)
87:   aload_1
88:   invokedynamic	#1.get (Lorg/springframework/beans/factory/BeanFactory;)Ljava/util/function/Supplier; (95)
93:   iconst_0
94:   anewarray		<org.springframework.beans.factory.config.BeanDefinitionCustomizer> (38)
97:   invokevirtual	org.springframework.context.support.GenericApplicationContext.registerBean (Ljava/lang/Class;Ljava/util/function/Supplier;[Lorg/springframework/beans/factory/config/BeanDefinitionCustomizer;)V (66)
100:  getstatic		java.lang.System.out Ljava/io/PrintStream; (18)
103:  ldc		":debug: Checking conditions before calling registerBean for bean factory method mustacheTemplateLoader" (97)
105:  invokevirtual	java.io.PrintStream.println (Ljava/lang/String;)V (26)
108:  aload_1
109:  invokevirtual	org.springframework.context.support.GenericApplicationContext.getBeanFactory ()Lorg/springframework/beans/factory/config/ConfigurableListableBeanFactory; (77)
112:  ldc		org.springframework.boot.autoconfigure.mustache.MustacheResourceTemplateLoader (99)
114:  invokeinterface	org.springframework.beans.factory.ListableBeanFactory.getBeanNamesForType (Ljava/lang/Class;)[Ljava/lang/String; (85)	2	0
119:  arraylength
120:  ifne		#147
123:  getstatic		java.lang.System.out Ljava/io/PrintStream; (18)
126:  ldc		":debug: Calling registerBean for bean factory method mustacheTemplateLoader" (101)
128:  invokevirtual	java.io.PrintStream.println (Ljava/lang/String;)V (26)
131:  aload_1
132:  ldc		org.springframework.boot.autoconfigure.mustache.MustacheResourceTemplateLoader (99)
134:  aload_1
135:  invokedynamic	#2.get (Lorg/springframework/beans/factory/BeanFactory;)Ljava/util/function/Supplier; (109)
140:  iconst_0
141:  anewarray		<org.springframework.beans.factory.config.BeanDefinitionCustomizer> (38)
144:  invokevirtual	org.springframework.context.support.GenericApplicationContext.registerBean (Ljava/lang/Class;Ljava/util/function/Supplier;[Lorg/springframework/beans/factory/config/BeanDefinitionCustomizer;)V (66)
147:  return


private static org.springframework.boot.autoconfigure.mustache.MustacheProperties init_MustacheProperties(org.springframework.beans.factory.BeanFactory arg0)
0:    new		<org.springframework.boot.autoconfigure.mustache.MustacheProperties> (40)
3:    dup
4:    invokespecial	org.springframework.boot.autoconfigure.mustache.MustacheProperties.<init> ()V (120)
7:    areturn

private static com.samskivert.mustache.Mustache$Compiler init_mustacheCompiler(org.springframework.beans.factory.BeanFactory arg0)
0:    getstatic		java.lang.System.out Ljava/io/PrintStream; (18)
3:    ldc		":debug: execution of lambda for mustacheCompiler" (122)
5:    invokevirtual	java.io.PrintStream.println (Ljava/lang/String;)V (26)
8:    aload_0
9:    ldc		org.springframework.boot.autoconfigure.mustache.MustacheAutoConfiguration (68)
11:   invokeinterface	org.springframework.beans.factory.BeanFactory.getBean (Ljava/lang/Class;)Ljava/lang/Object; (128)	2	0
16:   checkcast		<org.springframework.boot.autoconfigure.mustache.MustacheAutoConfiguration> (68)
19:   aload_0
20:   ldc		com.samskivert.mustache.Mustache$TemplateLoader (130)
22:   invokeinterface	org.springframework.beans.factory.BeanFactory.getBean (Ljava/lang/Class;)Ljava/lang/Object; (128)	2	0
27:   checkcast		<com.samskivert.mustache.Mustache$TemplateLoader> (130)
30:   invokevirtual	org.springframework.boot.autoconfigure.mustache.MustacheAutoConfiguration.mustacheCompiler (Lcom/samskivert/mustache/Mustache$TemplateLoader;)Lcom/samskivert/mustache/Mustache$Compiler; (134)
33:   areturn

private static org.springframework.boot.autoconfigure.mustache.MustacheResourceTemplateLoader init_mustacheTemplateLoader(org.springframework.beans.factory.BeanFactory arg0)
0:    getstatic		java.lang.System.out Ljava/io/PrintStream; (18)
3:    ldc		":debug: execution of lambda for mustacheTemplateLoader" (136)
5:    invokevirtual	java.io.PrintStream.println (Ljava/lang/String;)V (26)
8:    aload_0
9:    ldc		org.springframework.boot.autoconfigure.mustache.MustacheAutoConfiguration (68)
11:   invokeinterface	org.springframework.beans.factory.BeanFactory.getBean (Ljava/lang/Class;)Ljava/lang/Object; (128)	2	0
16:   checkcast		<org.springframework.boot.autoconfigure.mustache.MustacheAutoConfiguration> (68)
19:   invokevirtual	org.springframework.boot.autoconfigure.mustache.MustacheAutoConfiguration.mustacheTemplateLoader ()Lorg/springframework/boot/autoconfigure/mustache/MustacheResourceTemplateLoader; (139)
22:   areturn

