Classfile /Users/aclement/forks/spring-init-experiment/modules/library/target/classes/boot/autoconfigure/reactor/ReactorCoreAutoConfigurationModule$Initializer.class
  Last modified 22-Oct-2018; size 3089 bytes
  MD5 checksum 15cf9e188b47aa5455d649836005307c
  Compiled from "ReactorCoreAutoConfigurationModule.java"
class boot.autoconfigure.reactor.ReactorCoreAutoConfigurationModule$Initializer extends java.lang.Object implements org.springframework.context.ApplicationContextInitializer<org.springframework.context.support.GenericApplicationContext>
  minor version: 0
  major version: 52
  flags: ACC_SUPER
Constant pool:
    #1 = Methodref          #17.#50       // java/lang/Object."<init>":()V
    #2 = Methodref          #12.#51       // org/springframework/context/support/GenericApplicationContext.getBeanFactory:()Lorg/springframework/beans/factory/config/ConfigurableListableBeanFactory;
    #3 = Class              #52           // slim/ConditionService
    #4 = InterfaceMethodref #53.#54       // org/springframework/beans/factory/config/ConfigurableListableBeanFactory.getBean:(Ljava/lang/Class;)Ljava/lang/Object;
    #5 = Class              #55           // org/springframework/boot/autoconfigure/reactor/core/ReactorCoreAutoConfiguration
    #6 = InterfaceMethodref #3.#56        // slim/ConditionService.matches:(Ljava/lang/Class;)Z
    #7 = Class              #57           // org/springframework/boot/autoconfigure/reactor/core/ReactorCoreProperties
    #8 = InvokeDynamic      #0:#63        // #0:get:()Ljava/util/function/Supplier;
    #9 = Class              #64           // org/springframework/beans/factory/config/BeanDefinitionCustomizer
   #10 = Methodref          #12.#65       // org/springframework/context/support/GenericApplicationContext.registerBean:(Ljava/lang/Class;Ljava/util/function/Supplier;[Lorg/springframework/beans/factory/config/BeanDefinitionCustomizer;)V
   #11 = InvokeDynamic      #1:#63        // #1:get:()Ljava/util/function/Supplier;
   #12 = Class              #68           // org/springframework/context/support/GenericApplicationContext
   #13 = Methodref          #16.#69       // boot/autoconfigure/reactor/ReactorCoreAutoConfigurationModule$Initializer.initialize:(Lorg/springframework/context/support/GenericApplicationContext;)V
   #14 = Methodref          #5.#50        // org/springframework/boot/autoconfigure/reactor/core/ReactorCoreAutoConfiguration."<init>":()V
   #15 = Methodref          #7.#50        // org/springframework/boot/autoconfigure/reactor/core/ReactorCoreProperties."<init>":()V
   #16 = Class              #71           // boot/autoconfigure/reactor/ReactorCoreAutoConfigurationModule$Initializer
   #17 = Class              #72           // java/lang/Object
   #18 = Class              #73           // org/springframework/context/ApplicationContextInitializer
   #19 = Utf8               <init>
   #20 = Utf8               ()V
   #21 = Utf8               Code
   #22 = Utf8               LineNumberTable
   #23 = Utf8               LocalVariableTable
   #24 = Utf8               this
   #25 = Utf8               Initializer
   #26 = Utf8               InnerClasses
   #27 = Utf8               Lboot/autoconfigure/reactor/ReactorCoreAutoConfigurationModule$Initializer;
   #28 = Utf8               initialize
   #29 = Utf8               (Lorg/springframework/context/support/GenericApplicationContext;)V
   #30 = Utf8               context
   #31 = Utf8               Lorg/springframework/context/support/GenericApplicationContext;
   #32 = Utf8               conditions
   #33 = Utf8               Lslim/ConditionService;
   #34 = Utf8               StackMapTable
   #35 = Class              #52           // slim/ConditionService
   #36 = Utf8               MethodParameters
   #37 = Utf8               (Lorg/springframework/context/ConfigurableApplicationContext;)V
   #38 = Utf8               lambda$initialize$1
   #39 = Utf8               ()Lorg/springframework/boot/autoconfigure/reactor/core/ReactorCoreAutoConfiguration;
   #40 = Utf8               lambda$initialize$0
   #41 = Utf8               ()Lorg/springframework/boot/autoconfigure/reactor/core/ReactorCoreProperties;
   #42 = Utf8               Signature
   #43 = Utf8               Ljava/lang/Object;Lorg/springframework/context/ApplicationContextInitializer<Lorg/springframework/context/support/GenericApplicationContext;>;
   #44 = Utf8               SourceFile
   #45 = Utf8               ReactorCoreAutoConfigurationModule.java
   #46 = Utf8               RuntimeVisibleAnnotations
   #47 = Utf8               Lslim/InitializerMapping;
   #48 = Utf8               value
   #49 = Utf8               Lorg/springframework/boot/autoconfigure/reactor/core/ReactorCoreAutoConfiguration;
   #50 = NameAndType        #19:#20       // "<init>":()V
   #51 = NameAndType        #74:#75       // getBeanFactory:()Lorg/springframework/beans/factory/config/ConfigurableListableBeanFactory;
   #52 = Utf8               slim/ConditionService
   #53 = Class              #76           // org/springframework/beans/factory/config/ConfigurableListableBeanFactory
   #54 = NameAndType        #77:#78       // getBean:(Ljava/lang/Class;)Ljava/lang/Object;
   #55 = Utf8               org/springframework/boot/autoconfigure/reactor/core/ReactorCoreAutoConfiguration
   #56 = NameAndType        #79:#80       // matches:(Ljava/lang/Class;)Z
   #57 = Utf8               org/springframework/boot/autoconfigure/reactor/core/ReactorCoreProperties
   #58 = Utf8               BootstrapMethods
   #59 = MethodHandle       #6:#81        // invokestatic java/lang/invoke/LambdaMetafactory.metafactory:(Ljava/lang/invoke/MethodHandles$Lookup;Ljava/lang/String;Ljava/lang/invoke/MethodType;Ljava/lang/invoke/MethodType;Ljava/lang/invoke/MethodHandle;Ljava/lang/invoke/MethodType;)Ljava/lang/invoke/CallSite;
   #60 = MethodType         #82           //  ()Ljava/lang/Object;
   #61 = MethodHandle       #6:#83        // invokestatic boot/autoconfigure/reactor/ReactorCoreAutoConfigurationModule$Initializer.lambda$initialize$0:()Lorg/springframework/boot/autoconfigure/reactor/core/ReactorCoreProperties;
   #62 = MethodType         #41           //  ()Lorg/springframework/boot/autoconfigure/reactor/core/ReactorCoreProperties;
   #63 = NameAndType        #84:#85       // get:()Ljava/util/function/Supplier;
   #64 = Utf8               org/springframework/beans/factory/config/BeanDefinitionCustomizer
   #65 = NameAndType        #86:#87       // registerBean:(Ljava/lang/Class;Ljava/util/function/Supplier;[Lorg/springframework/beans/factory/config/BeanDefinitionCustomizer;)V
   #66 = MethodHandle       #6:#88        // invokestatic boot/autoconfigure/reactor/ReactorCoreAutoConfigurationModule$Initializer.lambda$initialize$1:()Lorg/springframework/boot/autoconfigure/reactor/core/ReactorCoreAutoConfiguration;
   #67 = MethodType         #39           //  ()Lorg/springframework/boot/autoconfigure/reactor/core/ReactorCoreAutoConfiguration;
   #68 = Utf8               org/springframework/context/support/GenericApplicationContext
   #69 = NameAndType        #28:#29       // initialize:(Lorg/springframework/context/support/GenericApplicationContext;)V
   #70 = Class              #89           // boot/autoconfigure/reactor/ReactorCoreAutoConfigurationModule
   #71 = Utf8               boot/autoconfigure/reactor/ReactorCoreAutoConfigurationModule$Initializer
   #72 = Utf8               java/lang/Object
   #73 = Utf8               org/springframework/context/ApplicationContextInitializer
   #74 = Utf8               getBeanFactory
   #75 = Utf8               ()Lorg/springframework/beans/factory/config/ConfigurableListableBeanFactory;
   #76 = Utf8               org/springframework/beans/factory/config/ConfigurableListableBeanFactory
   #77 = Utf8               getBean
   #78 = Utf8               (Ljava/lang/Class;)Ljava/lang/Object;
   #79 = Utf8               matches
   #80 = Utf8               (Ljava/lang/Class;)Z
   #81 = Methodref          #90.#91       // java/lang/invoke/LambdaMetafactory.metafactory:(Ljava/lang/invoke/MethodHandles$Lookup;Ljava/lang/String;Ljava/lang/invoke/MethodType;Ljava/lang/invoke/MethodType;Ljava/lang/invoke/MethodHandle;Ljava/lang/invoke/MethodType;)Ljava/lang/invoke/CallSite;
   #82 = Utf8               ()Ljava/lang/Object;
   #83 = Methodref          #16.#92       // boot/autoconfigure/reactor/ReactorCoreAutoConfigurationModule$Initializer.lambda$initialize$0:()Lorg/springframework/boot/autoconfigure/reactor/core/ReactorCoreProperties;
   #84 = Utf8               get
   #85 = Utf8               ()Ljava/util/function/Supplier;
   #86 = Utf8               registerBean
   #87 = Utf8               (Ljava/lang/Class;Ljava/util/function/Supplier;[Lorg/springframework/beans/factory/config/BeanDefinitionCustomizer;)V
   #88 = Methodref          #16.#93       // boot/autoconfigure/reactor/ReactorCoreAutoConfigurationModule$Initializer.lambda$initialize$1:()Lorg/springframework/boot/autoconfigure/reactor/core/ReactorCoreAutoConfiguration;
   #89 = Utf8               boot/autoconfigure/reactor/ReactorCoreAutoConfigurationModule
   #90 = Class              #94           // java/lang/invoke/LambdaMetafactory
   #91 = NameAndType        #95:#98       // metafactory:(Ljava/lang/invoke/MethodHandles$Lookup;Ljava/lang/String;Ljava/lang/invoke/MethodType;Ljava/lang/invoke/MethodType;Ljava/lang/invoke/MethodHandle;Ljava/lang/invoke/MethodType;)Ljava/lang/invoke/CallSite;
   #92 = NameAndType        #40:#41       // lambda$initialize$0:()Lorg/springframework/boot/autoconfigure/reactor/core/ReactorCoreProperties;
   #93 = NameAndType        #38:#39       // lambda$initialize$1:()Lorg/springframework/boot/autoconfigure/reactor/core/ReactorCoreAutoConfiguration;
   #94 = Utf8               java/lang/invoke/LambdaMetafactory
   #95 = Utf8               metafactory
   #96 = Class              #100          // java/lang/invoke/MethodHandles$Lookup
   #97 = Utf8               Lookup
   #98 = Utf8               (Ljava/lang/invoke/MethodHandles$Lookup;Ljava/lang/String;Ljava/lang/invoke/MethodType;Ljava/lang/invoke/MethodType;Ljava/lang/invoke/MethodHandle;Ljava/lang/invoke/MethodType;)Ljava/lang/invoke/CallSite;
   #99 = Class              #101          // java/lang/invoke/MethodHandles
  #100 = Utf8               java/lang/invoke/MethodHandles$Lookup
  #101 = Utf8               java/lang/invoke/MethodHandles
{
  boot.autoconfigure.reactor.ReactorCoreAutoConfigurationModule$Initializer();
    descriptor: ()V
    flags:
    Code:
      stack=1, locals=1, args_size=1
         0: aload_0
         1: invokespecial #1                  // Method java/lang/Object."<init>":()V
         4: return
      LineNumberTable:
        line 47: 0
      LocalVariableTable:
        Start  Length  Slot  Name   Signature
            0       5     0  this   Lboot/autoconfigure/reactor/ReactorCoreAutoConfigurationModule$Initializer;

  public void initialize(org.springframework.context.support.GenericApplicationContext);
    descriptor: (Lorg/springframework/context/support/GenericApplicationContext;)V
    flags: ACC_PUBLIC
    Code:
      stack=4, locals=3, args_size=2
         0: aload_1
         1: invokevirtual #2                  // Method org/springframework/context/support/GenericApplicationContext.getBeanFactory:()Lorg/springframework/beans/factory/config/ConfigurableListableBeanFactory;
         4: ldc           #3                  // class slim/ConditionService
         6: invokeinterface #4,  2            // InterfaceMethod org/springframework/beans/factory/config/ConfigurableListableBeanFactory.getBean:(Ljava/lang/Class;)Ljava/lang/Object;
        11: checkcast     #3                  // class slim/ConditionService
        14: astore_2
        15: aload_2
        16: ldc           #5                  // class org/springframework/boot/autoconfigure/reactor/core/ReactorCoreAutoConfiguration
        18: invokeinterface #6,  2            // InterfaceMethod slim/ConditionService.matches:(Ljava/lang/Class;)Z
        23: ifeq          56
        26: aload_1
        27: ldc           #7                  // class org/springframework/boot/autoconfigure/reactor/core/ReactorCoreProperties
        29: invokedynamic #8,  0              // InvokeDynamic #0:get:()Ljava/util/function/Supplier;
        34: iconst_0
        35: anewarray     #9                  // class org/springframework/beans/factory/config/BeanDefinitionCustomizer
        38: invokevirtual #10                 // Method org/springframework/context/support/GenericApplicationContext.registerBean:(Ljava/lang/Class;Ljava/util/function/Supplier;[Lorg/springframework/beans/factory/config/BeanDefinitionCustomizer;)V
        41: aload_1
        42: ldc           #5                  // class org/springframework/boot/autoconfigure/reactor/core/ReactorCoreAutoConfiguration
        44: invokedynamic #11,  0             // InvokeDynamic #1:get:()Ljava/util/function/Supplier;
        49: iconst_0
        50: anewarray     #9                  // class org/springframework/beans/factory/config/BeanDefinitionCustomizer
        53: invokevirtual #10                 // Method org/springframework/context/support/GenericApplicationContext.registerBean:(Ljava/lang/Class;Ljava/util/function/Supplier;[Lorg/springframework/beans/factory/config/BeanDefinitionCustomizer;)V
        56: return
      LineNumberTable:
        line 52: 0
        line 53: 6
        line 54: 15
        line 55: 26
        line 57: 41
        line 60: 56
      LocalVariableTable:
        Start  Length  Slot  Name   Signature
            0      57     0  this   Lboot/autoconfigure/reactor/ReactorCoreAutoConfigurationModule$Initializer;
            0      57     1 context   Lorg/springframework/context/support/GenericApplicationContext;
           15      42     2 conditions   Lslim/ConditionService;
      StackMapTable: number_of_entries = 1
        frame_type = 252 /* append */
          offset_delta = 56
          locals = [ class slim/ConditionService ]
    MethodParameters:
      Name                           Flags
      context

  public void initialize(org.springframework.context.ConfigurableApplicationContext);
    descriptor: (Lorg/springframework/context/ConfigurableApplicationContext;)V
    flags: ACC_PUBLIC, ACC_BRIDGE, ACC_SYNTHETIC
    Code:
      stack=2, locals=2, args_size=2
         0: aload_0
         1: aload_1
         2: checkcast     #12                 // class org/springframework/context/support/GenericApplicationContext
         5: invokevirtual #13                 // Method initialize:(Lorg/springframework/context/support/GenericApplicationContext;)V
         8: return
      LineNumberTable:
        line 46: 0
      LocalVariableTable:
        Start  Length  Slot  Name   Signature
            0       9     0  this   Lboot/autoconfigure/reactor/ReactorCoreAutoConfigurationModule$Initializer;
    MethodParameters:
      Name                           Flags
      context                        synthetic

  private static org.springframework.boot.autoconfigure.reactor.core.ReactorCoreAutoConfiguration lambda$initialize$1();
    descriptor: ()Lorg/springframework/boot/autoconfigure/reactor/core/ReactorCoreAutoConfiguration;
    flags: ACC_PRIVATE, ACC_STATIC, ACC_SYNTHETIC
    Code:
      stack=2, locals=0, args_size=0
         0: new           #5                  // class org/springframework/boot/autoconfigure/reactor/core/ReactorCoreAutoConfiguration
         3: dup
         4: invokespecial #14                 // Method org/springframework/boot/autoconfigure/reactor/core/ReactorCoreAutoConfiguration."<init>":()V
         7: areturn
      LineNumberTable:
        line 58: 0

  private static org.springframework.boot.autoconfigure.reactor.core.ReactorCoreProperties lambda$initialize$0();
    descriptor: ()Lorg/springframework/boot/autoconfigure/reactor/core/ReactorCoreProperties;
    flags: ACC_PRIVATE, ACC_STATIC, ACC_SYNTHETIC
    Code:
      stack=2, locals=0, args_size=0
         0: new           #7                  // class org/springframework/boot/autoconfigure/reactor/core/ReactorCoreProperties
         3: dup
         4: invokespecial #15                 // Method org/springframework/boot/autoconfigure/reactor/core/ReactorCoreProperties."<init>":()V
         7: areturn
      LineNumberTable:
        line 56: 0
}
Signature: #43                          // Ljava/lang/Object;Lorg/springframework/context/ApplicationContextInitializer<Lorg/springframework/context/support/GenericApplicationContext;>;
SourceFile: "ReactorCoreAutoConfigurationModule.java"
RuntimeVisibleAnnotations:
  0: #47(#48=[c#49])
InnerClasses:
     static #25= #16 of #70; //Initializer=class boot/autoconfigure/reactor/ReactorCoreAutoConfigurationModule$Initializer of class boot/autoconfigure/reactor/ReactorCoreAutoConfigurationModule
     public static final #97= #96 of #99; //Lookup=class java/lang/invoke/MethodHandles$Lookup of class java/lang/invoke/MethodHandles
BootstrapMethods:
  0: #59 invokestatic java/lang/invoke/LambdaMetafactory.metafactory:(Ljava/lang/invoke/MethodHandles$Lookup;Ljava/lang/String;Ljava/lang/invoke/MethodType;Ljava/lang/invoke/MethodType;Ljava/lang/invoke/MethodHandle;Ljava/lang/invoke/MethodType;)Ljava/lang/invoke/CallSite;
    Method arguments:
      #60 ()Ljava/lang/Object;
      #61 invokestatic boot/autoconfigure/reactor/ReactorCoreAutoConfigurationModule$Initializer.lambda$initialize$0:()Lorg/springframework/boot/autoconfigure/reactor/core/ReactorCoreProperties;
      #62 ()Lorg/springframework/boot/autoconfigure/reactor/core/ReactorCoreProperties;
  1: #59 invokestatic java/lang/invoke/LambdaMetafactory.metafactory:(Ljava/lang/invoke/MethodHandles$Lookup;Ljava/lang/String;Ljava/lang/invoke/MethodType;Ljava/lang/invoke/MethodType;Ljava/lang/invoke/MethodHandle;Ljava/lang/invoke/MethodType;)Ljava/lang/invoke/CallSite;
    Method arguments:
      #60 ()Ljava/lang/Object;
      #66 invokestatic boot/autoconfigure/reactor/ReactorCoreAutoConfigurationModule$Initializer.lambda$initialize$1:()Lorg/springframework/boot/autoconfigure/reactor/core/ReactorCoreAutoConfiguration;
      #67 ()Lorg/springframework/boot/autoconfigure/reactor/core/ReactorCoreAutoConfiguration;
