Classfile /Users/aclement/forks/spring-init-experiment/modules/library/target/classes/boot/autoconfigure/reactor/ReactorCoreAutoConfigurationModule.class
  Last modified 22-Oct-2018; size 1202 bytes
  MD5 checksum a65fbd5d18514013b2f5ece1c55ce00e
  Compiled from "ReactorCoreAutoConfigurationModule.java"
public class boot.autoconfigure.reactor.ReactorCoreAutoConfigurationModule implements slim.Module
  minor version: 0
  major version: 52
  flags: ACC_PUBLIC, ACC_SUPER
Constant pool:
   #1 = Methodref          #7.#29         // java/lang/Object."<init>":()V
   #2 = Class              #30            // org/springframework/context/ApplicationContextInitializer
   #3 = Class              #31            // boot/autoconfigure/reactor/ReactorCoreAutoConfigurationModule$Initializer
   #4 = Methodref          #3.#29         // boot/autoconfigure/reactor/ReactorCoreAutoConfigurationModule$Initializer."<init>":()V
   #5 = Methodref          #32.#33        // java/util/Arrays.asList:([Ljava/lang/Object;)Ljava/util/List;
   #6 = Class              #34            // boot/autoconfigure/reactor/ReactorCoreAutoConfigurationModule
   #7 = Class              #35            // java/lang/Object
   #8 = Class              #36            // slim/Module
   #9 = Utf8               Initializer
  #10 = Utf8               InnerClasses
  #11 = Utf8               <init>
  #12 = Utf8               ()V
  #13 = Utf8               Code
  #14 = Utf8               LineNumberTable
  #15 = Utf8               LocalVariableTable
  #16 = Utf8               this
  #17 = Utf8               Lboot/autoconfigure/reactor/ReactorCoreAutoConfigurationModule;
  #18 = Utf8               initializers
  #19 = Utf8               ()Ljava/util/List;
  #20 = Utf8               Signature
  #21 = Utf8               ()Ljava/util/List<Lorg/springframework/context/ApplicationContextInitializer<Lorg/springframework/context/support/GenericApplicationContext;>;>;
  #22 = Utf8               SourceFile
  #23 = Utf8               ReactorCoreAutoConfigurationModule.java
  #24 = Utf8               RuntimeVisibleAnnotations
  #25 = Utf8               Lorg/springframework/context/annotation/Configuration;
  #26 = Utf8               Lorg/springframework/context/annotation/Import;
  #27 = Utf8               value
  #28 = Utf8               Lorg/springframework/boot/autoconfigure/reactor/core/ReactorCoreAutoConfiguration;
  #29 = NameAndType        #11:#12        // "<init>":()V
  #30 = Utf8               org/springframework/context/ApplicationContextInitializer
  #31 = Utf8               boot/autoconfigure/reactor/ReactorCoreAutoConfigurationModule$Initializer
  #32 = Class              #37            // java/util/Arrays
  #33 = NameAndType        #38:#39        // asList:([Ljava/lang/Object;)Ljava/util/List;
  #34 = Utf8               boot/autoconfigure/reactor/ReactorCoreAutoConfigurationModule
  #35 = Utf8               java/lang/Object
  #36 = Utf8               slim/Module
  #37 = Utf8               java/util/Arrays
  #38 = Utf8               asList
  #39 = Utf8               ([Ljava/lang/Object;)Ljava/util/List;
{
  public boot.autoconfigure.reactor.ReactorCoreAutoConfigurationModule();
    descriptor: ()V
    flags: ACC_PUBLIC
    Code:
      stack=1, locals=1, args_size=1
         0: aload_0
         1: invokespecial #1                  // Method java/lang/Object."<init>":()V
         4: return
      LineNumberTable:
        line 39: 0
      LocalVariableTable:
        Start  Length  Slot  Name   Signature
            0       5     0  this   Lboot/autoconfigure/reactor/ReactorCoreAutoConfigurationModule;

  public java.util.List<org.springframework.context.ApplicationContextInitializer<org.springframework.context.support.GenericApplicationContext>> initializers();
    descriptor: ()Ljava/util/List;
    flags: ACC_PUBLIC
    Code:
      stack=5, locals=1, args_size=1
         0: iconst_1
         1: anewarray     #2                  // class org/springframework/context/ApplicationContextInitializer
         4: dup
         5: iconst_0
         6: new           #3                  // class boot/autoconfigure/reactor/ReactorCoreAutoConfigurationModule$Initializer
         9: dup
        10: invokespecial #4                  // Method boot/autoconfigure/reactor/ReactorCoreAutoConfigurationModule$Initializer."<init>":()V
        13: aastore
        14: invokestatic  #5                  // Method java/util/Arrays.asList:([Ljava/lang/Object;)Ljava/util/List;
        17: areturn
      LineNumberTable:
        line 43: 0
      LocalVariableTable:
        Start  Length  Slot  Name   Signature
            0      18     0  this   Lboot/autoconfigure/reactor/ReactorCoreAutoConfigurationModule;
    Signature: #21                          // ()Ljava/util/List<Lorg/springframework/context/ApplicationContextInitializer<Lorg/springframework/context/support/GenericApplicationContext;>;>;
}
SourceFile: "ReactorCoreAutoConfigurationModule.java"
RuntimeVisibleAnnotations:
  0: #25()
  1: #26(#27=[c#28])
InnerClasses:
     static #9= #3 of #6; //Initializer=class boot/autoconfigure/reactor/ReactorCoreAutoConfigurationModule$Initializer of class boot/autoconfigure/reactor/ReactorCoreAutoConfigurationModule
